[
  {
    "Type": "MaterialInstanceConstant",
    "Name": "MI_Umbra_Screen3",
    "Class": "UScriptClass'MaterialInstanceConstant'",
    "Properties": {
      "Parent": {
        "ObjectName": "Material'M_Umbra_Screen'",
        "ObjectPath": "DeadByDaylight/Content/Effects/Materials/Environment/Umbra/M_Umbra_Screen.0"
      },
      "bHasStaticPermutationResource": true,
      "ScalarParameterValues": [
        {
          "ParameterInfo": {
            "Name": "Brightness",
            "Association": "GlobalParameter",
            "Index": -1
          },
          "ParameterValue": 5.0,
          "ExpressionGUID": "158A1ADD-410A1FA8-A28C05B8-DDFDE011"
        },
        {
          "ParameterInfo": {
            "Name": "Emissive",
            "Association": "GlobalParameter",
            "Index": -1
          },
          "ParameterValue": 0.15,
          "ExpressionGUID": "7AA4A64B-43D20FD9-A561F986-B79B8B54"
        },
        {
          "ParameterInfo": {
            "Name": "Glitch Panner X",
            "Association": "GlobalParameter",
            "Index": -1
          },
          "ParameterValue": 1.1,
          "ExpressionGUID": "49E0F4C4-4FF96A3E-3A49859C-3BA832DD"
        },
        {
          "ParameterInfo": {
            "Name": "Glitch Panner Y",
            "Association": "GlobalParameter",
            "Index": -1
          },
          "ParameterValue": 0.0,
          "ExpressionGUID": "073CC25D-4435B395-54EECCBE-AA7BBC39"
        },
        {
          "ParameterInfo": {
            "Name": "Power (S)",
            "Association": "GlobalParameter",
            "Index": -1
          },
          "ParameterValue": 2.0,
          "ExpressionGUID": "BA44333A-435CED8E-A569E5B3-B3F4F6F6"
        },
        {
          "ParameterInfo": {
            "Name": "Power Base",
            "Association": "GlobalParameter",
            "Index": -1
          },
          "ParameterValue": 15.0,
          "ExpressionGUID": "7B39FABE-4E5C0632-F99E92BE-459322A0"
        },
        {
          "ParameterInfo": {
            "Name": "Power Lines",
            "Association": "GlobalParameter",
            "Index": -1
          },
          "ParameterValue": 30.0,
          "ExpressionGUID": "7C5B160F-4B4F1E9C-58E67A84-16109759"
        },
        {
          "ParameterInfo": {
            "Name": "RefractionDepthBias",
            "Association": "GlobalParameter",
            "Index": -1
          },
          "ParameterValue": 0.0,
          "ExpressionGUID": "00000000-00000000-00000000-00000000"
        }
      ],
      "VectorParameterValues": [
        {
          "ParameterInfo": {
            "Name": "Param",
            "Association": "GlobalParameter",
            "Index": -1
          },
          "ParameterValue": {
            "R": 0.02356543,
            "G": 0.12827958,
            "B": 0.1875,
            "A": 0.0,
            "Hex": "2A6478"
          },
          "ExpressionGUID": "9F7782A5-414D345F-8AC0FAAA-8860ECBD"
        },
        {
          "ParameterInfo": {
            "Name": "Param_1",
            "Association": "GlobalParameter",
            "Index": -1
          },
          "ParameterValue": {
            "R": 0.00268,
            "G": 0.0,
            "B": 0.01,
            "A": 1.0,
            "Hex": "FF080019"
          },
          "ExpressionGUID": "64240DF3-49AB0F35-EE0C35B8-9D8BC7FC"
        }
      ],
      "TextureParameterValues": [
        {
          "ParameterInfo": {
            "Name": "Texture",
            "Association": "GlobalParameter",
            "Index": -1
          },
          "ParameterValue": {
            "ObjectName": "Texture2D'T_UBA_ScreenDisplay03_02_BC'",
            "ObjectPath": "DeadByDaylight/Content/Textures/Environment/Umbra/Props/T_UBA_ScreenDisplay03_02_BC.0"
          },
          "ExpressionGUID": "47FF8653-480A3017-C518F398-1A9893EC"
        }
      ],
      "BasePropertyOverrides": {
        "TwoSided": true,
        "OpacityMaskClipValue": 0.3333
      },
      "StaticParameters": {
        "StaticSwitchParameters": [
          {
            "Value": true,
            "ParameterInfo": {
              "Name": "Invert Fresnel (B)",
              "Association": "GlobalParameter",
              "Index": -1
            },
            "bOverride": true,
            "ExpressionGUID": "731E3656-4BDFCB94-38B6B9B8-A9CCE5C8"
          },
          {
            "Value": false,
            "ParameterInfo": {
              "Name": "Use FlipBook",
              "Association": "GlobalParameter",
              "Index": -1
            },
            "bOverride": true,
            "ExpressionGUID": "581D6BE4-49D4CE29-C2B334AB-4B193DE7"
          }
        ]
      },
      "CachedReferencedTextures": [
        {
          "ObjectName": "Texture2D'T_Com_SteelRough_A_HRM'",
          "ObjectPath": "DeadByDaylight/Content/Textures/Environment/_Common/Tilable/Metal/T_Com_SteelRough_A_HRM.0"
        },
        {
          "ObjectName": "Texture2D'T_Umbra_Camp_Logo_Anim'",
          "ObjectPath": "DeadByDaylight/Content/Effects/Textures/Environment/Umbra/T_Umbra_Camp_Logo_Anim.0"
        },
        null,
        {
          "ObjectName": "Texture2D'DefaultDiffuse'",
          "ObjectPath": "Engine/Content/EngineMaterials/DefaultDiffuse.0"
        },
        {
          "ObjectName": "Texture2D'DebugNumberStrip'",
          "ObjectPath": "Engine/Content/Functions/Engine_MaterialFunctions02/ExampleContent/DebugNumberStrip.0"
        },
        {
          "ObjectName": "Texture2D'DebugNumberPeriod'",
          "ObjectPath": "Engine/Content/Functions/Engine_MaterialFunctions02/ExampleContent/Textures/DebugNumberPeriod.0"
        },
        {
          "ObjectName": "Texture2D'flipbook'",
          "ObjectPath": "Engine/Content/Functions/Engine_MaterialFunctions02/ExampleContent/Textures/flipbook.0"
        },
        {
          "ObjectName": "Texture2D'T_Perlin_Noise_M'",
          "ObjectPath": "DeadByDaylight/Content/StarterContent/Textures/T_Perlin_Noise_M.0"
        }
      ],
      "TextureStreamingData": [
        {
          "SamplingScale": 1.0,
          "UVChannelIndex": 0,
          "TextureName": "T_Com_SteelRough_A_HRM"
        }
      ]
    }
  }
]