[
  {
    "Type": "SkeletalMesh",
    "Name": "HS_Hair_ACC010_REF",
    "Properties": {
      "Skeleton": {
        "ObjectName": "Skeleton HS_Hair_ACC010_REF_Skeleton",
        "ObjectPath": "DeadByDaylight/Content/Characters/Campers/Haiti/Models/Heads/ACC/Tops/Skeletons/HS_Hair_ACC010_REF_Skeleton.0"
      },
      "LODInfo": [
        {
          "ScreenSize": {
            "bCooked": true,
            "Default": 1.5,
            "Value": 1.5
          },
          "LODHysteresis": 0.02,
          "LODMaterialMap": [],
          "BuildSettings": {
            "bRecomputeNormals": false,
            "bRecomputeTangents": true,
            "bUseMikkTSpace": false,
            "bComputeWeightedNormals": false,
            "bRemoveDegenerates": true,
            "bUseHighPrecisionTangentBasis": false,
            "bUseFullPrecisionUVs": false,
            "bBuildAdjacencyBuffer": true,
            "ThresholdPosition": 2E-05,
            "ThresholdTangentNormal": 2E-05,
            "ThresholdUV": 0.000977,
            "MorphThresholdPosition": 0.015
          },
          "ReductionSettings": {
            "TerminationCriterion": "SMTC_NumOfTriangles",
            "NumOfTrianglesPercentage": 1.0,
            "NumOfVertPercentage": 1.0,
            "MaxNumOfTriangles": 4,
            "MaxNumOfVerts": 6,
            "MaxDeviationPercentage": 0.0,
            "ReductionMethod": "SMOT_NumOfTriangles",
            "SilhouetteImportance": "SMOI_Normal",
            "TextureImportance": "SMOI_Normal",
            "ShadingImportance": "SMOI_Normal",
            "SkinningImportance": "SMOI_Normal",
            "bRemapMorphTargets": false,
            "bRecalcNormals": true,
            "WeldingThreshold": 0.1,
            "NormalsThreshold": 60.0,
            "MaxBonesPerVertex": 4,
            "bEnforceBoneBoundaries": false,
            "VolumeImportance": 1.0,
            "bLockEdges": false,
            "bLockColorBounaries": false,
            "BaseLOD": 0
          },
          "BonesToRemove": [],
          "BonesToPrioritize": [],
          "WeightOfPrioritization": 1.0,
          "BakePose": null,
          "BakePoseOverride": null,
          "SourceImportFilename": "",
          "SkinCacheUsage": "ESkinCacheUsage::Auto",
          "bHasBeenSimplified": false,
          "bHasPerLODVertexColors": false,
          "bAllowCPUAccess": false,
          "bSupportUniformlyDistributedSampling": false
        },
        {
          "ScreenSize": {
            "bCooked": true,
            "Default": 0.2,
            "Value": 0.2
          },
          "LODHysteresis": 0.02,
          "LODMaterialMap": [],
          "BuildSettings": {
            "bRecomputeNormals": true,
            "bRecomputeTangents": true,
            "bUseMikkTSpace": true,
            "bComputeWeightedNormals": false,
            "bRemoveDegenerates": true,
            "bUseHighPrecisionTangentBasis": false,
            "bUseFullPrecisionUVs": false,
            "bBuildAdjacencyBuffer": true,
            "ThresholdPosition": 2E-05,
            "ThresholdTangentNormal": 2E-05,
            "ThresholdUV": 0.0009765625,
            "MorphThresholdPosition": 0.015
          },
          "ReductionSettings": {
            "TerminationCriterion": "SMTC_NumOfTriangles",
            "NumOfTrianglesPercentage": 0.5,
            "NumOfVertPercentage": 0.5,
            "MaxNumOfTriangles": 4,
            "MaxNumOfVerts": 6,
            "MaxDeviationPercentage": 0.5,
            "ReductionMethod": "SMOT_NumOfTriangles",
            "SilhouetteImportance": "SMOI_Normal",
            "TextureImportance": "SMOI_Normal",
            "ShadingImportance": "SMOI_Normal",
            "SkinningImportance": "SMOI_Normal",
            "bRemapMorphTargets": false,
            "bRecalcNormals": true,
            "WeldingThreshold": 0.1,
            "NormalsThreshold": 60.0,
            "MaxBonesPerVertex": 3,
            "bEnforceBoneBoundaries": false,
            "VolumeImportance": 1.0,
            "bLockEdges": false,
            "bLockColorBounaries": false,
            "BaseLOD": 0
          },
          "BonesToRemove": [],
          "BonesToPrioritize": [],
          "WeightOfPrioritization": 1.0,
          "BakePose": null,
          "BakePoseOverride": null,
          "SourceImportFilename": "",
          "SkinCacheUsage": "ESkinCacheUsage::Auto",
          "bHasBeenSimplified": true,
          "bHasPerLODVertexColors": false,
          "bAllowCPUAccess": false,
          "bSupportUniformlyDistributedSampling": false
        },
        {
          "ScreenSize": {
            "bCooked": true,
            "Default": 0.05,
            "Value": 0.05
          },
          "LODHysteresis": 0.02,
          "LODMaterialMap": [],
          "BuildSettings": {
            "bRecomputeNormals": true,
            "bRecomputeTangents": true,
            "bUseMikkTSpace": true,
            "bComputeWeightedNormals": false,
            "bRemoveDegenerates": true,
            "bUseHighPrecisionTangentBasis": false,
            "bUseFullPrecisionUVs": false,
            "bBuildAdjacencyBuffer": true,
            "ThresholdPosition": 2E-05,
            "ThresholdTangentNormal": 2E-05,
            "ThresholdUV": 0.0009765625,
            "MorphThresholdPosition": 0.015
          },
          "ReductionSettings": {
            "TerminationCriterion": "SMTC_NumOfTriangles",
            "NumOfTrianglesPercentage": 0.15,
            "NumOfVertPercentage": 0.5,
            "MaxNumOfTriangles": 4,
            "MaxNumOfVerts": 6,
            "MaxDeviationPercentage": 0.5,
            "ReductionMethod": "SMOT_NumOfTriangles",
            "SilhouetteImportance": "SMOI_Normal",
            "TextureImportance": "SMOI_Normal",
            "ShadingImportance": "SMOI_Normal",
            "SkinningImportance": "SMOI_Normal",
            "bRemapMorphTargets": false,
            "bRecalcNormals": true,
            "WeldingThreshold": 0.01,
            "NormalsThreshold": 60.0,
            "MaxBonesPerVertex": 2,
            "bEnforceBoneBoundaries": false,
            "VolumeImportance": 1.0,
            "bLockEdges": false,
            "bLockColorBounaries": false,
            "BaseLOD": 0
          },
          "BonesToRemove": [],
          "BonesToPrioritize": [],
          "WeightOfPrioritization": 1.0,
          "BakePose": null,
          "BakePoseOverride": null,
          "SourceImportFilename": "",
          "SkinCacheUsage": "ESkinCacheUsage::Auto",
          "bHasBeenSimplified": true,
          "bHasPerLODVertexColors": false,
          "bAllowCPUAccess": false,
          "bSupportUniformlyDistributedSampling": false
        },
        {
          "ScreenSize": {
            "bCooked": true,
            "Default": 0.01,
            "Value": 0.01
          },
          "LODHysteresis": 0.02,
          "LODMaterialMap": [],
          "BuildSettings": {
            "bRecomputeNormals": true,
            "bRecomputeTangents": true,
            "bUseMikkTSpace": true,
            "bComputeWeightedNormals": false,
            "bRemoveDegenerates": true,
            "bUseHighPrecisionTangentBasis": false,
            "bUseFullPrecisionUVs": false,
            "bBuildAdjacencyBuffer": true,
            "ThresholdPosition": 2E-05,
            "ThresholdTangentNormal": 2E-05,
            "ThresholdUV": 0.0009765625,
            "MorphThresholdPosition": 0.015
          },
          "ReductionSettings": {
            "TerminationCriterion": "SMTC_NumOfTriangles",
            "NumOfTrianglesPercentage": 0.3,
            "NumOfVertPercentage": 0.5,
            "MaxNumOfTriangles": 4,
            "MaxNumOfVerts": 6,
            "MaxDeviationPercentage": 0.5,
            "ReductionMethod": "SMOT_NumOfTriangles",
            "SilhouetteImportance": "SMOI_Normal",
            "TextureImportance": "SMOI_Normal",
            "ShadingImportance": "SMOI_Normal",
            "SkinningImportance": "SMOI_Normal",
            "bRemapMorphTargets": false,
            "bRecalcNormals": true,
            "WeldingThreshold": 0.1,
            "NormalsThreshold": 60.0,
            "MaxBonesPerVertex": 1,
            "bEnforceBoneBoundaries": false,
            "VolumeImportance": 1.0,
            "bLockEdges": false,
            "bLockColorBounaries": false,
            "BaseLOD": 2
          },
          "BonesToRemove": [
            {
              "BoneName": "joint_FacialGroup"
            }
          ],
          "BonesToPrioritize": [],
          "WeightOfPrioritization": 1.0,
          "BakePose": null,
          "BakePoseOverride": null,
          "SourceImportFilename": "",
          "SkinCacheUsage": "ESkinCacheUsage::Auto",
          "bHasBeenSimplified": true,
          "bHasPerLODVertexColors": false,
          "bAllowCPUAccess": false,
          "bSupportUniformlyDistributedSampling": false
        }
      ],
      "MinLod": {
        "bCooked": true,
        "Default": 0,
        "Value": 0
      },
      "bHasBeenSimplified": true,
      "bHasVertexColors": true,
      "PhysicsAsset": {
        "ObjectName": "PhysicsAsset HS_Hair_ACC010_REF_PhysicsAsset",
        "ObjectPath": "DeadByDaylight/Content/Characters/Campers/Haiti/Models/Heads/ACC/Tops/Physics/HS_Hair_ACC010_REF_PhysicsAsset.0"
      },
      "SamplingInfo": {
        "BuiltData": {
          "WholeMeshBuiltData": [
            {
              "AreaWeightedTriangleSampler": {
                "Prob": [],
                "Alias": [],
                "TotalWeight": 0.0
              }
            },
            {
              "AreaWeightedTriangleSampler": {
                "Prob": [],
                "Alias": [],
                "TotalWeight": 0.0
              }
            },
            {
              "AreaWeightedTriangleSampler": {
                "Prob": [],
                "Alias": [],
                "TotalWeight": 0.0
              }
            },
            {
              "AreaWeightedTriangleSampler": {
                "Prob": [],
                "Alias": [],
                "TotalWeight": 0.0
              }
            }
          ]
        }
      }
    },
    "ImportedBounds": {
      "Origin": {
        "X": 0.0,
        "Y": 3.4606056,
        "Z": 168.68024
      },
      "BoxExtent": {
        "X": 8.224385,
        "Y": 10.944026,
        "Z": 14.262245
      },
      "SphereRadius": 19.769266
    },
    "Materials": [
      {
        "ObjectName": "MaterialInstanceConstant MI_HSBeard010",
        "ObjectPath": "DeadByDaylight/Content/Characters/Campers/Haiti/Materials/Outfit010/MI_HSBeard010.0"
      },
      {
        "ObjectName": "MaterialInstanceConstant MI_HSHair010",
        "ObjectPath": "DeadByDaylight/Content/Characters/Campers/Haiti/Materials/Outfit010/MI_HSHair010.0"
      },
      {
        "ObjectName": "MaterialInstanceConstant MI_HSHeadACC010",
        "ObjectPath": "DeadByDaylight/Content/Characters/Campers/Haiti/Materials/Outfit010/MI_HSHeadACC010.0"
      }
    ],
    "LODModels": [
      {
        "Sections": [
          {
            "MaterialIndex": 0,
            "BaseIndex": 0,
            "NumTriangles": 1716,
            "bRecomputeTangent": false,
            "RecomputeTangentsVertexMaskChannel": "Green",
            "bCastShadow": true,
            "bVisibleInRayTracing": true,
            "bLegacyClothingSection": false,
            "CorrespondClothSectionIndex": -1,
            "BaseVertexIndex": 0,
            "NumVertices": 2157,
            "MaxBoneInfluences": 7,
            "bUse16BitBoneIndex": false,
            "CorrespondClothAssetIndex": -1,
            "bDisabled": false,
            "GenerateUpToLodIndex": -1,
            "OriginalDataSectionIndex": -1,
            "ChunkedParentSectionIndex": -1
          },
          {
            "MaterialIndex": 1,
            "BaseIndex": 5148,
            "NumTriangles": 7516,
            "bRecomputeTangent": false,
            "RecomputeTangentsVertexMaskChannel": "Green",
            "bCastShadow": true,
            "bVisibleInRayTracing": true,
            "bLegacyClothingSection": false,
            "CorrespondClothSectionIndex": -1,
            "BaseVertexIndex": 2157,
            "NumVertices": 6231,
            "MaxBoneInfluences": 1,
            "bUse16BitBoneIndex": false,
            "CorrespondClothAssetIndex": -1,
            "bDisabled": false,
            "GenerateUpToLodIndex": -1,
            "OriginalDataSectionIndex": -1,
            "ChunkedParentSectionIndex": -1
          },
          {
            "MaterialIndex": 2,
            "BaseIndex": 27696,
            "NumTriangles": 120,
            "bRecomputeTangent": false,
            "RecomputeTangentsVertexMaskChannel": "Green",
            "bCastShadow": true,
            "bVisibleInRayTracing": true,
            "bLegacyClothingSection": false,
            "CorrespondClothSectionIndex": -1,
            "BaseVertexIndex": 8388,
            "NumVertices": 151,
            "MaxBoneInfluences": 1,
            "bUse16BitBoneIndex": false,
            "CorrespondClothAssetIndex": -1,
            "bDisabled": false,
            "GenerateUpToLodIndex": -1,
            "OriginalDataSectionIndex": -1,
            "ChunkedParentSectionIndex": -1
          }
        ],
        "NumVertices": 8539,
        "NumTexCoords": 1,
        "VertexBufferGPUSkin": {
          "NumTexCoords": 0,
          "MeshExtension": {
            "X": 0.0,
            "Y": 0.0,
            "Z": 0.0
          },
          "MeshOrigin": {
            "X": 0.0,
            "Y": 0.0,
            "Z": 0.0
          },
          "bUseFullPrecisionUVs": true,
          "bExtraBoneInfluences": false
        }
      },
      {
        "Sections": [
          {
            "MaterialIndex": 0,
            "BaseIndex": 0,
            "NumTriangles": 678,
            "bRecomputeTangent": false,
            "RecomputeTangentsVertexMaskChannel": "Green",
            "bCastShadow": true,
            "bVisibleInRayTracing": true,
            "bLegacyClothingSection": false,
            "CorrespondClothSectionIndex": -1,
            "BaseVertexIndex": 0,
            "NumVertices": 1255,
            "MaxBoneInfluences": 3,
            "bUse16BitBoneIndex": false,
            "CorrespondClothAssetIndex": -1,
            "bDisabled": false,
            "GenerateUpToLodIndex": -1,
            "OriginalDataSectionIndex": -1,
            "ChunkedParentSectionIndex": -1
          },
          {
            "MaterialIndex": 1,
            "BaseIndex": 2034,
            "NumTriangles": 3926,
            "bRecomputeTangent": false,
            "RecomputeTangentsVertexMaskChannel": "Green",
            "bCastShadow": true,
            "bVisibleInRayTracing": true,
            "bLegacyClothingSection": false,
            "CorrespondClothSectionIndex": -1,
            "BaseVertexIndex": 1255,
            "NumVertices": 3886,
            "MaxBoneInfluences": 1,
            "bUse16BitBoneIndex": false,
            "CorrespondClothAssetIndex": -1,
            "bDisabled": false,
            "GenerateUpToLodIndex": -1,
            "OriginalDataSectionIndex": -1,
            "ChunkedParentSectionIndex": -1
          },
          {
            "MaterialIndex": 2,
            "BaseIndex": 13812,
            "NumTriangles": 70,
            "bRecomputeTangent": false,
            "RecomputeTangentsVertexMaskChannel": "Green",
            "bCastShadow": true,
            "bVisibleInRayTracing": true,
            "bLegacyClothingSection": false,
            "CorrespondClothSectionIndex": -1,
            "BaseVertexIndex": 5141,
            "NumVertices": 102,
            "MaxBoneInfluences": 1,
            "bUse16BitBoneIndex": false,
            "CorrespondClothAssetIndex": -1,
            "bDisabled": false,
            "GenerateUpToLodIndex": -1,
            "OriginalDataSectionIndex": -1,
            "ChunkedParentSectionIndex": -1
          }
        ],
        "NumVertices": 5243,
        "NumTexCoords": 1,
        "VertexBufferGPUSkin": {
          "NumTexCoords": 0,
          "MeshExtension": {
            "X": 0.0,
            "Y": 0.0,
            "Z": 0.0
          },
          "MeshOrigin": {
            "X": 0.0,
            "Y": 0.0,
            "Z": 0.0
          },
          "bUseFullPrecisionUVs": true,
          "bExtraBoneInfluences": false
        }
      },
      {
        "Sections": [
          {
            "MaterialIndex": 0,
            "BaseIndex": 0,
            "NumTriangles": 440,
            "bRecomputeTangent": false,
            "RecomputeTangentsVertexMaskChannel": "Green",
            "bCastShadow": true,
            "bVisibleInRayTracing": true,
            "bLegacyClothingSection": false,
            "CorrespondClothSectionIndex": -1,
            "BaseVertexIndex": 0,
            "NumVertices": 880,
            "MaxBoneInfluences": 2,
            "bUse16BitBoneIndex": false,
            "CorrespondClothAssetIndex": -1,
            "bDisabled": false,
            "GenerateUpToLodIndex": -1,
            "OriginalDataSectionIndex": -1,
            "ChunkedParentSectionIndex": -1
          },
          {
            "MaterialIndex": 1,
            "BaseIndex": 1320,
            "NumTriangles": 948,
            "bRecomputeTangent": false,
            "RecomputeTangentsVertexMaskChannel": "Green",
            "bCastShadow": true,
            "bVisibleInRayTracing": true,
            "bLegacyClothingSection": false,
            "CorrespondClothSectionIndex": -1,
            "BaseVertexIndex": 880,
            "NumVertices": 1233,
            "MaxBoneInfluences": 1,
            "bUse16BitBoneIndex": false,
            "CorrespondClothAssetIndex": -1,
            "bDisabled": false,
            "GenerateUpToLodIndex": -1,
            "OriginalDataSectionIndex": -1,
            "ChunkedParentSectionIndex": -1
          },
          {
            "MaterialIndex": 2,
            "BaseIndex": 4164,
            "NumTriangles": 14,
            "bRecomputeTangent": false,
            "RecomputeTangentsVertexMaskChannel": "Green",
            "bCastShadow": true,
            "bVisibleInRayTracing": true,
            "bLegacyClothingSection": false,
            "CorrespondClothSectionIndex": -1,
            "BaseVertexIndex": 2113,
            "NumVertices": 35,
            "MaxBoneInfluences": 1,
            "bUse16BitBoneIndex": false,
            "CorrespondClothAssetIndex": -1,
            "bDisabled": false,
            "GenerateUpToLodIndex": -1,
            "OriginalDataSectionIndex": -1,
            "ChunkedParentSectionIndex": -1
          }
        ],
        "NumVertices": 2148,
        "NumTexCoords": 1,
        "VertexBufferGPUSkin": {
          "NumTexCoords": 0,
          "MeshExtension": {
            "X": 0.0,
            "Y": 0.0,
            "Z": 0.0
          },
          "MeshOrigin": {
            "X": 0.0,
            "Y": 0.0,
            "Z": 0.0
          },
          "bUseFullPrecisionUVs": true,
          "bExtraBoneInfluences": false
        }
      },
      {
        "Sections": [
          {
            "MaterialIndex": 0,
            "BaseIndex": 0,
            "NumTriangles": 316,
            "bRecomputeTangent": false,
            "RecomputeTangentsVertexMaskChannel": "Green",
            "bCastShadow": true,
            "bVisibleInRayTracing": true,
            "bLegacyClothingSection": false,
            "CorrespondClothSectionIndex": -1,
            "BaseVertexIndex": 0,
            "NumVertices": 636,
            "MaxBoneInfluences": 1,
            "bUse16BitBoneIndex": false,
            "CorrespondClothAssetIndex": -1,
            "bDisabled": false,
            "GenerateUpToLodIndex": -1,
            "OriginalDataSectionIndex": -1,
            "ChunkedParentSectionIndex": -1
          },
          {
            "MaterialIndex": 1,
            "BaseIndex": 948,
            "NumTriangles": 104,
            "bRecomputeTangent": false,
            "RecomputeTangentsVertexMaskChannel": "Green",
            "bCastShadow": true,
            "bVisibleInRayTracing": true,
            "bLegacyClothingSection": false,
            "CorrespondClothSectionIndex": -1,
            "BaseVertexIndex": 636,
            "NumVertices": 177,
            "MaxBoneInfluences": 1,
            "bUse16BitBoneIndex": false,
            "CorrespondClothAssetIndex": -1,
            "bDisabled": false,
            "GenerateUpToLodIndex": -1,
            "OriginalDataSectionIndex": -1,
            "ChunkedParentSectionIndex": -1
          }
        ],
        "NumVertices": 813,
        "NumTexCoords": 1,
        "VertexBufferGPUSkin": {
          "NumTexCoords": 0,
          "MeshExtension": {
            "X": 0.0,
            "Y": 0.0,
            "Z": 0.0
          },
          "MeshOrigin": {
            "X": 0.0,
            "Y": 0.0,
            "Z": 0.0
          },
          "bUseFullPrecisionUVs": true,
          "bExtraBoneInfluences": false
        }
      }
    ]
  }
]