[
  {
    "Type": "Texture2D",
    "Name": "DF_Torso04_PandaTVChampKraken",
    "Class": "UScriptClass'Texture2D'",
    "Properties": {
      "ImportedSize": {
        "X": 512,
        "Y": 512
      },
      "LightingGuid": "1EB4A238-4011A7C8-1D21BDB2-B222B51A",
      "LODGroup": "TextureGroup::TEXTUREGROUP_UI"
    },
    "SizeX": 512,
    "SizeY": 512,
    "PackedData": 1,
    "PixelFormat": "PF_DXT5",
    "FirstMipToSerialize": 0,
    "Mips": [
      {
        "BulkData": {
          "BulkDataFlags": "BULKDATA_SingleUse | BULKDATA_ForceInlinePayload",
          "ElementCount": 262144,
          "SizeOnDisk": 262144,
          "OffsetInFile": "0x6F"
        },
        "SizeX": 512,
        "SizeY": 512,
        "SizeZ": 1
      }
    ]
  }
]