[
  {
    "Type": "BodySetup",
    "Name": "BodySetup_1",
    "Outer": "SM_CHU_BookPile05",
    "Class": "UScriptClass'BodySetup'",
    "Properties": {
      "AggGeom": {
        "BoxElems": [
          {
            "Center": {
              "X": 1.6098404,
              "Y": 2.4806213,
              "Z": 51.257584
            },
            "Rotation": {
              "Pitch": -90.0,
              "Yaw": 0.0,
              "Roll": -90.0
            },
            "X": 151.80753,
            "Y": 71.129776,
            "Z": 34.047775,
            "RestOffset": 0.0,
            "Name": "None",
            "bContributeToMass": true,
            "CollisionEnabled": "ECollisionEnabled::QueryAndPhysics"
          }
        ]
      },
      "DefaultInstance": {
        "ObjectType": "ECollisionChannel::ECC_WorldStatic",
        "CollisionProfileName": "BlockAll",
        "CollisionResponses": {
          "ResponseArray": [
            {
              "Channel": "Interactable",
              "Response": "ECollisionResponse::ECR_Block"
            },
            {
              "Channel": "Slasher",
              "Response": "ECollisionResponse::ECR_Block"
            },
            {
              "Channel": "Blood",
              "Response": "ECollisionResponse::ECR_Block"
            },
            {
              "Channel": "InteractionDetector",
              "Response": "ECollisionResponse::ECR_Ignore"
            },
            {
              "Channel": "BlinkBlocker",
              "Response": "ECollisionResponse::ECR_Ignore"
            },
            {
              "Channel": "Ground",
              "Response": "ECollisionResponse::ECR_Ignore"
            },
            {
              "Channel": "Walkable",
              "Response": "ECollisionResponse::ECR_Block"
            }
          ]
        }
      },
      "CollisionTraceFlag": "ECollisionTraceFlag::CTF_UseSimpleAsComplex"
    },
    "BodySetupGuid": "F942E5BC483D6D2000A652B054E7A5A6",
    "CookedFormatData": {
      "PhysXPC": {
        "BulkDataFlags": "BULKDATA_SingleUse | BULKDATA_ForceInlinePayload",
        "ElementCount": 28,
        "SizeOnDisk": 28,
        "OffsetInFile": "0xDD"
      }
    }
  },
  {
    "Type": "NavCollision",
    "Name": "NavCollision_2",
    "Outer": "SM_CHU_BookPile05",
    "Class": "UScriptClass'NavCollision'",
    "CookedFormatData": {
      "NavCollision_Chaos": {
        "BulkDataFlags": "BULKDATA_SingleUse | BULKDATA_ForceInlinePayload",
        "ElementCount": 361,
        "SizeOnDisk": 361,
        "OffsetInFile": "0x32"
      }
    }
  },
  {
    "Type": "StaticMesh",
    "Name": "SM_CHU_BookPile05",
    "Class": "UScriptClass'StaticMesh'",
    "Properties": {
      "MinLod": {
        "bCooked": true,
        "Default": 0,
        "Value": 0
      },
      "ShadowMaxLOD": {
        "PerDetailModeValue": [
          {
            "Key": "Ultra",
            "Value": 3
          },
          {
            "Key": "High",
            "Value": 3
          },
          {
            "Key": "Medium",
            "Value": 3
          },
          {
            "Key": "Low",
            "Value": 3
          },
          {
            "Key": "Mobile",
            "Value": 3
          }
        ]
      },
      "StaticMaterials": [
        {
          "MaterialInterface": {
            "ObjectName": "MaterialInstanceConstant'MI_COM_Books01'",
            "ObjectPath": "/Game/Materials/Instances/Common/Props/MI_COM_Books01.0"
          },
          "MaterialSlotName": "MI_WAL_Books13",
          "ImportedMaterialSlotName": "MI_WAL_Books13",
          "UVChannelData": {
            "bInitialized": true,
            "bOverrideDensities": false,
            "LocalUVDensities": 205.77281,
            "LocalUVDensities": 321.69107,
            "LocalUVDensities": 0.0,
            "LocalUVDensities": 0.0
          }
        }
      ],
      "LightmapUVDensity": 321.69107,
      "LightMapResolution": 64,
      "LightMapCoordinateIndex": 1,
      "LODForCollision": 3,
      "ExtendedBounds": {
        "Origin": {
          "X": 3.9054527,
          "Y": 2.9869719,
          "Z": 46.96007
        },
        "BoxExtent": {
          "X": 37.567772,
          "Y": 19.549793,
          "Z": 71.311775
        },
        "SphereRadius": 79.64438233869038
      }
    },
    "BodySetup": {
      "ObjectName": "BodySetup'SM_CHU_BookPile05:BodySetup_1'",
      "ObjectPath": "/Game/Meshes/Environment/Churros/Props/SM_CHU_BookPile05.0"
    },
    "NavCollision": {
      "ObjectName": "NavCollision'SM_CHU_BookPile05:NavCollision_2'",
      "ObjectPath": "/Game/Meshes/Environment/Churros/Props/SM_CHU_BookPile05.1"
    },
    "LightingGuid": "C8182A11-4573A042-5C6508B3-A8B59D34",
    "RenderData": {
      "LODs": [
        {
          "Sections": [
            {
              "MaterialIndex": 0,
              "FirstIndex": 0,
              "NumTriangles": 2738,
              "MinVertexIndex": 0,
              "MaxVertexIndex": 6429,
              "bEnableCollision": true,
              "bCastShadow": true,
              "bForceOpaque": false,
              "bVisibleInRayTracing": true
            }
          ],
          "MaxDeviation": 0.0,
          "PositionVertexBuffer": {
            "Stride": 12,
            "NumVertices": 6430
          },
          "VertexBuffer": {
            "NumTexCoords": 2,
            "NumVertices": 6430,
            "Strides": -1,
            "UseHighPrecisionTangentBasis": false,
            "UseFullPrecisionUVs": false
          },
          "ColorVertexBuffer": {
            "Stride": 0,
            "NumVertices": 0
          },
          "CardRepresentationData": {
            "Bounds": {
              "Min": {
                "X": -34.66232,
                "Y": -17.56282,
                "Z": -25.351704
              },
              "Max": {
                "X": 42.473225,
                "Y": 23.536766,
                "Z": 119.27185
              },
              "IsValid": 1
            },
            "MaxLodLevel": 0,
            "bMostlyTwoSided": false,
            "CardBuildData": [
              {
                "OBB": {
                  "AxisX": {
                    "X": 0.0,
                    "Y": 1.0,
                    "Z": 0.0
                  },
                  "AxisY": {
                    "X": 0.0,
                    "Y": 0.0,
                    "Z": 1.0
                  },
                  "AxisZ": {
                    "X": -1.0,
                    "Y": 0.0,
                    "Z": 0.0
                  },
                  "Origin": {
                    "X": -1.0945473,
                    "Y": 2.9869728,
                    "Z": 46.96007
                  },
                  "Extent": {
                    "X": 20.0,
                    "Y": 70.0,
                    "Z": 40.0
                  }
                },
                "LODLevel": 0,
                "AxisAlignedDirectionIndex": 0
              },
              {
                "OBB": {
                  "AxisX": {
                    "X": 0.0,
                    "Y": 1.0,
                    "Z": 0.0
                  },
                  "AxisY": {
                    "X": 0.0,
                    "Y": 0.0,
                    "Z": 1.0
                  },
                  "AxisZ": {
                    "X": 1.0,
                    "Y": 0.0,
                    "Z": 0.0
                  },
                  "Origin": {
                    "X": 8.905453,
                    "Y": 2.9869728,
                    "Z": 46.96007
                  },
                  "Extent": {
                    "X": 20.0,
                    "Y": 70.0,
                    "Z": 40.0
                  }
                },
                "LODLevel": 0,
                "AxisAlignedDirectionIndex": 1
              },
              {
                "OBB": {
                  "AxisX": {
                    "X": 1.0,
                    "Y": 0.0,
                    "Z": 0.0
                  },
                  "AxisY": {
                    "X": 0.0,
                    "Y": 0.0,
                    "Z": 1.0
                  },
                  "AxisZ": {
                    "X": 0.0,
                    "Y": -1.0,
                    "Z": 0.0
                  },
                  "Origin": {
                    "X": 3.9054527,
                    "Y": -2.0130272,
                    "Z": 46.96007
                  },
                  "Extent": {
                    "X": 38.567772,
                    "Y": 70.0,
                    "Z": 20.0
                  }
                },
                "LODLevel": 0,
                "AxisAlignedDirectionIndex": 2
              },
              {
                "OBB": {
                  "AxisX": {
                    "X": 1.0,
                    "Y": 0.0,
                    "Z": 0.0
                  },
                  "AxisY": {
                    "X": 0.0,
                    "Y": 0.0,
                    "Z": 1.0
                  },
                  "AxisZ": {
                    "X": 0.0,
                    "Y": 1.0,
                    "Z": 0.0
                  },
                  "Origin": {
                    "X": 3.9054527,
                    "Y": 2.9869728,
                    "Z": 46.96007
                  },
                  "Extent": {
                    "X": 38.567772,
                    "Y": 70.0,
                    "Z": 25.0
                  }
                },
                "LODLevel": 0,
                "AxisAlignedDirectionIndex": 3
              },
              {
                "OBB": {
                  "AxisX": {
                    "X": 1.0,
                    "Y": 0.0,
                    "Z": 0.0
                  },
                  "AxisY": {
                    "X": 0.0,
                    "Y": 1.0,
                    "Z": 0.0
                  },
                  "AxisZ": {
                    "X": 0.0,
                    "Y": 0.0,
                    "Z": -1.0
                  },
                  "Origin": {
                    "X": 3.9054527,
                    "Y": 2.9869728,
                    "Z": 41.96007
                  },
                  "Extent": {
                    "X": 38.567772,
                    "Y": 20.0,
                    "Z": 70.0
                  }
                },
                "LODLevel": 0,
                "AxisAlignedDirectionIndex": 4
              },
              {
                "OBB": {
                  "AxisX": {
                    "X": 1.0,
                    "Y": 0.0,
                    "Z": 0.0
                  },
                  "AxisY": {
                    "X": 0.0,
                    "Y": 1.0,
                    "Z": 0.0
                  },
                  "AxisZ": {
                    "X": 0.0,
                    "Y": 0.0,
                    "Z": 1.0
                  },
                  "Origin": {
                    "X": 3.9054527,
                    "Y": 2.9869728,
                    "Z": 51.960068
                  },
                  "Extent": {
                    "X": 38.567772,
                    "Y": 20.0,
                    "Z": 70.0
                  }
                },
                "LODLevel": 0,
                "AxisAlignedDirectionIndex": 5
              }
            ]
          }
        },
        {
          "Sections": [
            {
              "MaterialIndex": 0,
              "FirstIndex": 0,
              "NumTriangles": 1680,
              "MinVertexIndex": 0,
              "MaxVertexIndex": 4131,
              "bEnableCollision": true,
              "bCastShadow": true,
              "bForceOpaque": false,
              "bVisibleInRayTracing": true
            }
          ],
          "MaxDeviation": 0.0,
          "PositionVertexBuffer": {
            "Stride": 12,
            "NumVertices": 4132
          },
          "VertexBuffer": {
            "NumTexCoords": 2,
            "NumVertices": 4132,
            "Strides": -1,
            "UseHighPrecisionTangentBasis": false,
            "UseFullPrecisionUVs": false
          },
          "ColorVertexBuffer": {
            "Stride": 0,
            "NumVertices": 0
          }
        },
        {
          "Sections": [
            {
              "MaterialIndex": 0,
              "FirstIndex": 0,
              "NumTriangles": 1342,
              "MinVertexIndex": 0,
              "MaxVertexIndex": 3209,
              "bEnableCollision": true,
              "bCastShadow": true,
              "bForceOpaque": false,
              "bVisibleInRayTracing": true
            }
          ],
          "MaxDeviation": 1.4482529,
          "PositionVertexBuffer": {
            "Stride": 12,
            "NumVertices": 3210
          },
          "VertexBuffer": {
            "NumTexCoords": 2,
            "NumVertices": 3210,
            "Strides": -1,
            "UseHighPrecisionTangentBasis": false,
            "UseFullPrecisionUVs": false
          },
          "ColorVertexBuffer": {
            "Stride": 0,
            "NumVertices": 0
          }
        },
        {
          "Sections": [
            {
              "MaterialIndex": 0,
              "FirstIndex": 0,
              "NumTriangles": 1260,
              "MinVertexIndex": 0,
              "MaxVertexIndex": 3011,
              "bEnableCollision": true,
              "bCastShadow": true,
              "bForceOpaque": false,
              "bVisibleInRayTracing": true
            }
          ],
          "MaxDeviation": 1.5081369,
          "PositionVertexBuffer": {
            "Stride": 12,
            "NumVertices": 3012
          },
          "VertexBuffer": {
            "NumTexCoords": 2,
            "NumVertices": 3012,
            "Strides": -1,
            "UseHighPrecisionTangentBasis": false,
            "UseFullPrecisionUVs": false
          },
          "ColorVertexBuffer": {
            "Stride": 0,
            "NumVertices": 0
          }
        }
      ],
      "NaniteResources": {
        "RootData": null,
        "StreamablePages": {
          "BulkDataFlags": "BULKDATA_None",
          "ElementCount": 0,
          "SizeOnDisk": 0,
          "OffsetInFile": "0x9C24B"
        },
        "ImposterAtlas": [],
        "HierarchyNodes": [],
        "HierarchyRootOffsets": [],
        "PageStreamingStates": [],
        "PageDependencies": [],
        "NumRootPages": 0,
        "PositionPrecision": 0,
        "NormalPrecision": 0,
        "TangentPrecision": 0,
        "NumInputTriangles": 0,
        "NumInputVertices": 0,
        "NumInputMeshes": 0,
        "NumInputTexCoords": 0,
        "NumClusters": 0,
        "ResourceFlags": 0
      },
      "Bounds": {
        "Origin": {
          "X": 3.9054527,
          "Y": 2.9869719,
          "Z": 46.96007
        },
        "BoxExtent": {
          "X": 37.567772,
          "Y": 19.549793,
          "Z": 71.311775
        },
        "SphereRadius": 79.64438
      },
      "bLODsShareStaticLighting": false,
      "ScreenSize": [
        1.0,
        0.7,
        0.2,
        0.08,
        0.0,
        0.0,
        0.0,
        0.0
      ]
    }
  }
]