[
  {
    "Type": "Texture2D",
    "Name": "T_UI_tooltipRarityBackground_legendary",
    "Class": "UScriptClass'Texture2D'",
    "Properties": {
      "ImportedSize": {
        "X": 512,
        "Y": 452
      },
      "LightingGuid": "C21FB1C1-4AC2EC58-ECA452B9-D359BDEB",
      "LODGroup": "TextureGroup::TEXTUREGROUP_UI",
      "NeverStream": true
    },
    "SizeX": 512,
    "SizeY": 452,
    "PackedData": 1,
    "PixelFormat": "PF_DXT5",
    "FirstMipToSerialize": 0,
    "Mips": [
      {
        "BulkData": {
          "BulkDataFlags": "BULKDATA_SingleUse | BULKDATA_ForceInlinePayload",
          "ElementCount": 231424,
          "SizeOnDisk": 231424,
          "OffsetInFile": "0x72"
        },
        "SizeX": 512,
        "SizeY": 452,
        "SizeZ": 1
      }
    ]
  }
]