[
  {
    "Type": "AnimSequence",
    "Name": "GK_Grab_Obstacles_FT_FPV",
    "Class": "UScriptClass'AnimSequence'",
    "Properties": {
      "NumFrames": 81,
      "TrackToSkeletonMapTable": [
        {
          "BoneTreeIndex": 0
        },
        {
          "BoneTreeIndex": 1
        },
        {
          "BoneTreeIndex": 47
        },
        {
          "BoneTreeIndex": 71
        },
        {
          "BoneTreeIndex": 72
        },
        {
          "BoneTreeIndex": 73
        },
        {
          "BoneTreeIndex": 74
        },
        {
          "BoneTreeIndex": 184
        },
        {
          "BoneTreeIndex": 48
        },
        {
          "BoneTreeIndex": 49
        },
        {
          "BoneTreeIndex": 50
        },
        {
          "BoneTreeIndex": 51
        },
        {
          "BoneTreeIndex": 185
        },
        {
          "BoneTreeIndex": 2
        },
        {
          "BoneTreeIndex": 3
        },
        {
          "BoneTreeIndex": 4
        },
        {
          "BoneTreeIndex": 5
        },
        {
          "BoneTreeIndex": 126
        },
        {
          "BoneTreeIndex": 127
        },
        {
          "BoneTreeIndex": 94
        },
        {
          "BoneTreeIndex": 95
        },
        {
          "BoneTreeIndex": 96
        },
        {
          "BoneTreeIndex": 97
        },
        {
          "BoneTreeIndex": 98
        },
        {
          "BoneTreeIndex": 99
        },
        {
          "BoneTreeIndex": 100
        },
        {
          "BoneTreeIndex": 117
        },
        {
          "BoneTreeIndex": 118
        },
        {
          "BoneTreeIndex": 119
        },
        {
          "BoneTreeIndex": 112
        },
        {
          "BoneTreeIndex": 113
        },
        {
          "BoneTreeIndex": 114
        },
        {
          "BoneTreeIndex": 107
        },
        {
          "BoneTreeIndex": 108
        },
        {
          "BoneTreeIndex": 109
        },
        {
          "BoneTreeIndex": 102
        },
        {
          "BoneTreeIndex": 103
        },
        {
          "BoneTreeIndex": 104
        },
        {
          "BoneTreeIndex": 122
        },
        {
          "BoneTreeIndex": 123
        },
        {
          "BoneTreeIndex": 124
        },
        {
          "BoneTreeIndex": 186
        },
        {
          "BoneTreeIndex": 6
        },
        {
          "BoneTreeIndex": 159
        },
        {
          "BoneTreeIndex": 160
        },
        {
          "BoneTreeIndex": 128
        },
        {
          "BoneTreeIndex": 129
        },
        {
          "BoneTreeIndex": 130
        },
        {
          "BoneTreeIndex": 131
        },
        {
          "BoneTreeIndex": 132
        },
        {
          "BoneTreeIndex": 133
        },
        {
          "BoneTreeIndex": 134
        },
        {
          "BoneTreeIndex": 151
        },
        {
          "BoneTreeIndex": 152
        },
        {
          "BoneTreeIndex": 153
        },
        {
          "BoneTreeIndex": 146
        },
        {
          "BoneTreeIndex": 147
        },
        {
          "BoneTreeIndex": 148
        },
        {
          "BoneTreeIndex": 141
        },
        {
          "BoneTreeIndex": 142
        },
        {
          "BoneTreeIndex": 143
        },
        {
          "BoneTreeIndex": 136
        },
        {
          "BoneTreeIndex": 137
        },
        {
          "BoneTreeIndex": 138
        },
        {
          "BoneTreeIndex": 455
        },
        {
          "BoneTreeIndex": 456
        },
        {
          "BoneTreeIndex": 457
        },
        {
          "BoneTreeIndex": 458
        },
        {
          "BoneTreeIndex": 158
        },
        {
          "BoneTreeIndex": 157
        },
        {
          "BoneTreeIndex": 187
        },
        {
          "BoneTreeIndex": 7
        },
        {
          "BoneTreeIndex": 8
        },
        {
          "BoneTreeIndex": 9
        },
        {
          "BoneTreeIndex": 16
        },
        {
          "BoneTreeIndex": 17
        },
        {
          "BoneTreeIndex": 30
        },
        {
          "BoneTreeIndex": 33
        },
        {
          "BoneTreeIndex": 34
        },
        {
          "BoneTreeIndex": 459
        },
        {
          "BoneTreeIndex": 460
        },
        {
          "BoneTreeIndex": 461
        },
        {
          "BoneTreeIndex": 462
        },
        {
          "BoneTreeIndex": 463
        },
        {
          "BoneTreeIndex": 464
        },
        {
          "BoneTreeIndex": 465
        },
        {
          "BoneTreeIndex": 466
        },
        {
          "BoneTreeIndex": 467
        },
        {
          "BoneTreeIndex": 468
        },
        {
          "BoneTreeIndex": 469
        },
        {
          "BoneTreeIndex": 470
        },
        {
          "BoneTreeIndex": 471
        },
        {
          "BoneTreeIndex": 472
        },
        {
          "BoneTreeIndex": 473
        },
        {
          "BoneTreeIndex": 474
        },
        {
          "BoneTreeIndex": 10
        },
        {
          "BoneTreeIndex": 475
        },
        {
          "BoneTreeIndex": 476
        },
        {
          "BoneTreeIndex": 477
        },
        {
          "BoneTreeIndex": 478
        },
        {
          "BoneTreeIndex": 31
        },
        {
          "BoneTreeIndex": 37
        },
        {
          "BoneTreeIndex": 40
        },
        {
          "BoneTreeIndex": 479
        },
        {
          "BoneTreeIndex": 480
        },
        {
          "BoneTreeIndex": 481
        },
        {
          "BoneTreeIndex": 482
        },
        {
          "BoneTreeIndex": 483
        },
        {
          "BoneTreeIndex": 484
        },
        {
          "BoneTreeIndex": 485
        },
        {
          "BoneTreeIndex": 486
        },
        {
          "BoneTreeIndex": 453
        },
        {
          "BoneTreeIndex": 454
        },
        {
          "BoneTreeIndex": 452
        },
        {
          "BoneTreeIndex": 171
        },
        {
          "BoneTreeIndex": 176
        },
        {
          "BoneTreeIndex": 177
        },
        {
          "BoneTreeIndex": 172
        },
        {
          "BoneTreeIndex": 173
        },
        {
          "BoneTreeIndex": 174
        },
        {
          "BoneTreeIndex": 175
        },
        {
          "BoneTreeIndex": 179
        },
        {
          "BoneTreeIndex": 178
        }
      ],
      "BoneCompressionSettings": {
        "ObjectName": "AnimBoneCompressionSettings'DefaultAnimBoneCompressionSettings'",
        "ObjectPath": "Engine/Content/Animation/DefaultAnimBoneCompressionSettings.0"
      },
      "CurveCompressionSettings": {
        "ObjectName": "AnimCurveCompressionSettings'DefaultAnimCurveCompressionSettings'",
        "ObjectPath": "Engine/Content/Animation/DefaultAnimCurveCompressionSettings.1"
      },
      "Notifies": [
        {
          "TriggerTimeOffset": 0.0,
          "EndTriggerTimeOffset": 0.0,
          "TriggerWeightThreshold": 1E-05,
          "NotifyName": "FX_MakeBombDisappear",
          "Notify": null,
          "NotifyStateClass": null,
          "Duration": 0.0,
          "EndLink": {
            "LinkedMontage": null,
            "SlotIndex": 0,
            "SegmentIndex": -1,
            "LinkMethod": "EAnimLinkMethod::Absolute",
            "CachedLinkMethod": "EAnimLinkMethod::Absolute",
            "SegmentBeginTime": 0.0,
            "SegmentLength": 0.0,
            "LinkValue": 0.093777835,
            "LinkedSequence": null
          },
          "bConvertedFromBranchingPoint": false,
          "MontageTickType": "EMontageNotifyTickType::Queued",
          "NotifyTriggerChance": 1.0,
          "NotifyFilterType": "ENotifyFilterType::NoFiltering",
          "NotifyFilterLOD": 0,
          "bTriggerOnDedicatedServer": true,
          "bTriggerOnFollower": false,
          "TrackIndex": 0,
          "LinkedMontage": null,
          "SlotIndex": 0,
          "SegmentIndex": 0,
          "LinkMethod": "EAnimLinkMethod::Absolute",
          "CachedLinkMethod": "EAnimLinkMethod::Absolute",
          "SegmentBeginTime": 0.0,
          "SegmentLength": 2.6666667,
          "LinkValue": 0.093777835,
          "LinkedSequence": {
            "ObjectName": "AnimSequence'GK_Grab_Obstacles_FT_FPV'",
            "ObjectPath": "DeadByDaylight/Content/Characters/Slashers/Guam/AnimSequences/Interactions/GK_Grab_Obstacles_FT_FPV.0"
          }
        },
        {
          "TriggerTimeOffset": 0.0,
          "EndTriggerTimeOffset": 0.0,
          "TriggerWeightThreshold": 1E-05,
          "NotifyName": "Audio_Killer_Walk_Footstep_Right",
          "Notify": null,
          "NotifyStateClass": null,
          "Duration": 0.0,
          "EndLink": {
            "LinkedMontage": null,
            "SlotIndex": 0,
            "SegmentIndex": -1,
            "LinkMethod": "EAnimLinkMethod::Absolute",
            "CachedLinkMethod": "EAnimLinkMethod::Absolute",
            "SegmentBeginTime": 0.0,
            "SegmentLength": 0.0,
            "LinkValue": 0.13933319,
            "LinkedSequence": null
          },
          "bConvertedFromBranchingPoint": false,
          "MontageTickType": "EMontageNotifyTickType::Queued",
          "NotifyTriggerChance": 1.0,
          "NotifyFilterType": "ENotifyFilterType::NoFiltering",
          "NotifyFilterLOD": 0,
          "bTriggerOnDedicatedServer": true,
          "bTriggerOnFollower": false,
          "TrackIndex": 1,
          "LinkedMontage": null,
          "SlotIndex": 0,
          "SegmentIndex": 0,
          "LinkMethod": "EAnimLinkMethod::Absolute",
          "CachedLinkMethod": "EAnimLinkMethod::Absolute",
          "SegmentBeginTime": 0.0,
          "SegmentLength": 2.6666667,
          "LinkValue": 0.13933319,
          "LinkedSequence": {
            "ObjectName": "AnimSequence'GK_Grab_Obstacles_FT_FPV'",
            "ObjectPath": "DeadByDaylight/Content/Characters/Slashers/Guam/AnimSequences/Interactions/GK_Grab_Obstacles_FT_FPV.0"
          }
        },
        {
          "TriggerTimeOffset": 0.0,
          "EndTriggerTimeOffset": 0.0,
          "TriggerWeightThreshold": 1E-05,
          "NotifyName": "Audio_Killer_Body_Shuffle_Low",
          "Notify": null,
          "NotifyStateClass": null,
          "Duration": 0.0,
          "EndLink": {
            "LinkedMontage": null,
            "SlotIndex": 0,
            "SegmentIndex": -1,
            "LinkMethod": "EAnimLinkMethod::Absolute",
            "CachedLinkMethod": "EAnimLinkMethod::Absolute",
            "SegmentBeginTime": 0.0,
            "SegmentLength": 0.0,
            "LinkValue": 0.14203443,
            "LinkedSequence": null
          },
          "bConvertedFromBranchingPoint": false,
          "MontageTickType": "EMontageNotifyTickType::Queued",
          "NotifyTriggerChance": 1.0,
          "NotifyFilterType": "ENotifyFilterType::NoFiltering",
          "NotifyFilterLOD": 0,
          "bTriggerOnDedicatedServer": true,
          "bTriggerOnFollower": false,
          "TrackIndex": 2,
          "LinkedMontage": null,
          "SlotIndex": 0,
          "SegmentIndex": 0,
          "LinkMethod": "EAnimLinkMethod::Absolute",
          "CachedLinkMethod": "EAnimLinkMethod::Absolute",
          "SegmentBeginTime": 0.0,
          "SegmentLength": 2.6666667,
          "LinkValue": 0.14203443,
          "LinkedSequence": {
            "ObjectName": "AnimSequence'GK_Grab_Obstacles_FT_FPV'",
            "ObjectPath": "DeadByDaylight/Content/Characters/Slashers/Guam/AnimSequences/Interactions/GK_Grab_Obstacles_FT_FPV.0"
          }
        },
        {
          "TriggerTimeOffset": 0.0,
          "EndTriggerTimeOffset": 0.0,
          "TriggerWeightThreshold": 1E-05,
          "NotifyName": "Audio_Killer_Walk_Footstep_Left",
          "Notify": null,
          "NotifyStateClass": null,
          "Duration": 0.0,
          "EndLink": {
            "LinkedMontage": null,
            "SlotIndex": 0,
            "SegmentIndex": -1,
            "LinkMethod": "EAnimLinkMethod::Absolute",
            "CachedLinkMethod": "EAnimLinkMethod::Absolute",
            "SegmentBeginTime": 0.0,
            "SegmentLength": 0.0,
            "LinkValue": 0.29915494,
            "LinkedSequence": null
          },
          "bConvertedFromBranchingPoint": false,
          "MontageTickType": "EMontageNotifyTickType::Queued",
          "NotifyTriggerChance": 1.0,
          "NotifyFilterType": "ENotifyFilterType::NoFiltering",
          "NotifyFilterLOD": 0,
          "bTriggerOnDedicatedServer": true,
          "bTriggerOnFollower": false,
          "TrackIndex": 1,
          "LinkedMontage": null,
          "SlotIndex": 0,
          "SegmentIndex": 0,
          "LinkMethod": "EAnimLinkMethod::Absolute",
          "CachedLinkMethod": "EAnimLinkMethod::Absolute",
          "SegmentBeginTime": 0.0,
          "SegmentLength": 2.6666667,
          "LinkValue": 0.29915494,
          "LinkedSequence": {
            "ObjectName": "AnimSequence'GK_Grab_Obstacles_FT_FPV'",
            "ObjectPath": "DeadByDaylight/Content/Characters/Slashers/Guam/AnimSequences/Interactions/GK_Grab_Obstacles_FT_FPV.0"
          }
        },
        {
          "TriggerTimeOffset": 0.0,
          "EndTriggerTimeOffset": 0.0,
          "TriggerWeightThreshold": 1E-05,
          "NotifyName": "Audio_Killer_Body_Shuffle_Low",
          "Notify": null,
          "NotifyStateClass": null,
          "Duration": 0.0,
          "EndLink": {
            "LinkedMontage": null,
            "SlotIndex": 0,
            "SegmentIndex": -1,
            "LinkMethod": "EAnimLinkMethod::Absolute",
            "CachedLinkMethod": "EAnimLinkMethod::Absolute",
            "SegmentBeginTime": 0.0,
            "SegmentLength": 0.0,
            "LinkValue": 0.30518728,
            "LinkedSequence": null
          },
          "bConvertedFromBranchingPoint": false,
          "MontageTickType": "EMontageNotifyTickType::Queued",
          "NotifyTriggerChance": 1.0,
          "NotifyFilterType": "ENotifyFilterType::NoFiltering",
          "NotifyFilterLOD": 0,
          "bTriggerOnDedicatedServer": true,
          "bTriggerOnFollower": false,
          "TrackIndex": 2,
          "LinkedMontage": null,
          "SlotIndex": 0,
          "SegmentIndex": 0,
          "LinkMethod": "EAnimLinkMethod::Absolute",
          "CachedLinkMethod": "EAnimLinkMethod::Absolute",
          "SegmentBeginTime": 0.0,
          "SegmentLength": 2.6666667,
          "LinkValue": 0.30518728,
          "LinkedSequence": {
            "ObjectName": "AnimSequence'GK_Grab_Obstacles_FT_FPV'",
            "ObjectPath": "DeadByDaylight/Content/Characters/Slashers/Guam/AnimSequences/Interactions/GK_Grab_Obstacles_FT_FPV.0"
          }
        },
        {
          "TriggerTimeOffset": 0.0,
          "EndTriggerTimeOffset": 0.0,
          "TriggerWeightThreshold": 1E-05,
          "NotifyName": "Audio_Killer_Body_Move",
          "Notify": null,
          "NotifyStateClass": null,
          "Duration": 0.0,
          "EndLink": {
            "LinkedMontage": null,
            "SlotIndex": 0,
            "SegmentIndex": -1,
            "LinkMethod": "EAnimLinkMethod::Absolute",
            "CachedLinkMethod": "EAnimLinkMethod::Absolute",
            "SegmentBeginTime": 0.0,
            "SegmentLength": 0.0,
            "LinkValue": 0.46832374,
            "LinkedSequence": null
          },
          "bConvertedFromBranchingPoint": false,
          "MontageTickType": "EMontageNotifyTickType::Queued",
          "NotifyTriggerChance": 1.0,
          "NotifyFilterType": "ENotifyFilterType::NoFiltering",
          "NotifyFilterLOD": 0,
          "bTriggerOnDedicatedServer": true,
          "bTriggerOnFollower": false,
          "TrackIndex": 1,
          "LinkedMontage": null,
          "SlotIndex": 0,
          "SegmentIndex": 0,
          "LinkMethod": "EAnimLinkMethod::Absolute",
          "CachedLinkMethod": "EAnimLinkMethod::Absolute",
          "SegmentBeginTime": 0.0,
          "SegmentLength": 2.6666667,
          "LinkValue": 0.46832374,
          "LinkedSequence": {
            "ObjectName": "AnimSequence'GK_Grab_Obstacles_FT_FPV'",
            "ObjectPath": "DeadByDaylight/Content/Characters/Slashers/Guam/AnimSequences/Interactions/GK_Grab_Obstacles_FT_FPV.0"
          }
        },
        {
          "TriggerTimeOffset": 0.0,
          "EndTriggerTimeOffset": 0.0,
          "TriggerWeightThreshold": 1E-05,
          "NotifyName": "Audio_Killer_Walk_Footstep_Left",
          "Notify": null,
          "NotifyStateClass": null,
          "Duration": 0.0,
          "EndLink": {
            "LinkedMontage": null,
            "SlotIndex": 0,
            "SegmentIndex": -1,
            "LinkMethod": "EAnimLinkMethod::Absolute",
            "CachedLinkMethod": "EAnimLinkMethod::Absolute",
            "SegmentBeginTime": 0.0,
            "SegmentLength": 0.0,
            "LinkValue": 1.1678332,
            "LinkedSequence": null
          },
          "bConvertedFromBranchingPoint": false,
          "MontageTickType": "EMontageNotifyTickType::Queued",
          "NotifyTriggerChance": 1.0,
          "NotifyFilterType": "ENotifyFilterType::NoFiltering",
          "NotifyFilterLOD": 0,
          "bTriggerOnDedicatedServer": true,
          "bTriggerOnFollower": false,
          "TrackIndex": 1,
          "LinkedMontage": null,
          "SlotIndex": 0,
          "SegmentIndex": 0,
          "LinkMethod": "EAnimLinkMethod::Absolute",
          "CachedLinkMethod": "EAnimLinkMethod::Absolute",
          "SegmentBeginTime": 0.0,
          "SegmentLength": 2.6666667,
          "LinkValue": 1.1678332,
          "LinkedSequence": {
            "ObjectName": "AnimSequence'GK_Grab_Obstacles_FT_FPV'",
            "ObjectPath": "DeadByDaylight/Content/Characters/Slashers/Guam/AnimSequences/Interactions/GK_Grab_Obstacles_FT_FPV.0"
          }
        },
        {
          "TriggerTimeOffset": 0.0,
          "EndTriggerTimeOffset": 0.0,
          "TriggerWeightThreshold": 1E-05,
          "NotifyName": "Audio_Killer_Body_Shuffle_Low",
          "Notify": null,
          "NotifyStateClass": null,
          "Duration": 0.0,
          "EndLink": {
            "LinkedMontage": null,
            "SlotIndex": 0,
            "SegmentIndex": -1,
            "LinkMethod": "EAnimLinkMethod::Absolute",
            "CachedLinkMethod": "EAnimLinkMethod::Absolute",
            "SegmentBeginTime": 0.0,
            "SegmentLength": 0.0,
            "LinkValue": 1.1698499,
            "LinkedSequence": null
          },
          "bConvertedFromBranchingPoint": false,
          "MontageTickType": "EMontageNotifyTickType::Queued",
          "NotifyTriggerChance": 1.0,
          "NotifyFilterType": "ENotifyFilterType::NoFiltering",
          "NotifyFilterLOD": 0,
          "bTriggerOnDedicatedServer": true,
          "bTriggerOnFollower": false,
          "TrackIndex": 2,
          "LinkedMontage": null,
          "SlotIndex": 0,
          "SegmentIndex": 0,
          "LinkMethod": "EAnimLinkMethod::Absolute",
          "CachedLinkMethod": "EAnimLinkMethod::Absolute",
          "SegmentBeginTime": 0.0,
          "SegmentLength": 2.6666667,
          "LinkValue": 1.1698499,
          "LinkedSequence": {
            "ObjectName": "AnimSequence'GK_Grab_Obstacles_FT_FPV'",
            "ObjectPath": "DeadByDaylight/Content/Characters/Slashers/Guam/AnimSequences/Interactions/GK_Grab_Obstacles_FT_FPV.0"
          }
        },
        {
          "TriggerTimeOffset": 0.0,
          "EndTriggerTimeOffset": 0.0,
          "TriggerWeightThreshold": 1E-05,
          "NotifyName": "Audio_Killer_Walk_Footstep_Right",
          "Notify": null,
          "NotifyStateClass": null,
          "Duration": 0.0,
          "EndLink": {
            "LinkedMontage": null,
            "SlotIndex": 0,
            "SegmentIndex": -1,
            "LinkMethod": "EAnimLinkMethod::Absolute",
            "CachedLinkMethod": "EAnimLinkMethod::Absolute",
            "SegmentBeginTime": 0.0,
            "SegmentLength": 0.0,
            "LinkValue": 1.4814814,
            "LinkedSequence": null
          },
          "bConvertedFromBranchingPoint": false,
          "MontageTickType": "EMontageNotifyTickType::Queued",
          "NotifyTriggerChance": 1.0,
          "NotifyFilterType": "ENotifyFilterType::NoFiltering",
          "NotifyFilterLOD": 0,
          "bTriggerOnDedicatedServer": true,
          "bTriggerOnFollower": false,
          "TrackIndex": 1,
          "LinkedMontage": null,
          "SlotIndex": 0,
          "SegmentIndex": 0,
          "LinkMethod": "EAnimLinkMethod::Absolute",
          "CachedLinkMethod": "EAnimLinkMethod::Absolute",
          "SegmentBeginTime": 0.0,
          "SegmentLength": 2.6666667,
          "LinkValue": 1.4814814,
          "LinkedSequence": {
            "ObjectName": "AnimSequence'GK_Grab_Obstacles_FT_FPV'",
            "ObjectPath": "DeadByDaylight/Content/Characters/Slashers/Guam/AnimSequences/Interactions/GK_Grab_Obstacles_FT_FPV.0"
          }
        },
        {
          "TriggerTimeOffset": 0.0,
          "EndTriggerTimeOffset": 0.0,
          "TriggerWeightThreshold": 1E-05,
          "NotifyName": "Audio_Killer_Body_Shuffle_Low",
          "Notify": null,
          "NotifyStateClass": null,
          "Duration": 0.0,
          "EndLink": {
            "LinkedMontage": null,
            "SlotIndex": 0,
            "SegmentIndex": -1,
            "LinkMethod": "EAnimLinkMethod::Absolute",
            "CachedLinkMethod": "EAnimLinkMethod::Absolute",
            "SegmentBeginTime": 0.0,
            "SegmentLength": 0.0,
            "LinkValue": 1.4833243,
            "LinkedSequence": null
          },
          "bConvertedFromBranchingPoint": false,
          "MontageTickType": "EMontageNotifyTickType::Queued",
          "NotifyTriggerChance": 1.0,
          "NotifyFilterType": "ENotifyFilterType::NoFiltering",
          "NotifyFilterLOD": 0,
          "bTriggerOnDedicatedServer": true,
          "bTriggerOnFollower": false,
          "TrackIndex": 2,
          "LinkedMontage": null,
          "SlotIndex": 0,
          "SegmentIndex": 0,
          "LinkMethod": "EAnimLinkMethod::Absolute",
          "CachedLinkMethod": "EAnimLinkMethod::Absolute",
          "SegmentBeginTime": 0.0,
          "SegmentLength": 2.6666667,
          "LinkValue": 1.4833243,
          "LinkedSequence": {
            "ObjectName": "AnimSequence'GK_Grab_Obstacles_FT_FPV'",
            "ObjectPath": "DeadByDaylight/Content/Characters/Slashers/Guam/AnimSequences/Interactions/GK_Grab_Obstacles_FT_FPV.0"
          }
        },
        {
          "TriggerTimeOffset": 0.0,
          "EndTriggerTimeOffset": 0.0,
          "TriggerWeightThreshold": 1E-05,
          "NotifyName": "Audio_Killer_Walk_Footstep_Left",
          "Notify": null,
          "NotifyStateClass": null,
          "Duration": 0.0,
          "EndLink": {
            "LinkedMontage": null,
            "SlotIndex": 0,
            "SegmentIndex": -1,
            "LinkMethod": "EAnimLinkMethod::Absolute",
            "CachedLinkMethod": "EAnimLinkMethod::Absolute",
            "SegmentBeginTime": 0.0,
            "SegmentLength": 0.0,
            "LinkValue": 1.734556,
            "LinkedSequence": null
          },
          "bConvertedFromBranchingPoint": false,
          "MontageTickType": "EMontageNotifyTickType::Queued",
          "NotifyTriggerChance": 1.0,
          "NotifyFilterType": "ENotifyFilterType::NoFiltering",
          "NotifyFilterLOD": 0,
          "bTriggerOnDedicatedServer": true,
          "bTriggerOnFollower": false,
          "TrackIndex": 1,
          "LinkedMontage": null,
          "SlotIndex": 0,
          "SegmentIndex": 0,
          "LinkMethod": "EAnimLinkMethod::Absolute",
          "CachedLinkMethod": "EAnimLinkMethod::Absolute",
          "SegmentBeginTime": 0.0,
          "SegmentLength": 2.6666667,
          "LinkValue": 1.734556,
          "LinkedSequence": {
            "ObjectName": "AnimSequence'GK_Grab_Obstacles_FT_FPV'",
            "ObjectPath": "DeadByDaylight/Content/Characters/Slashers/Guam/AnimSequences/Interactions/GK_Grab_Obstacles_FT_FPV.0"
          }
        },
        {
          "TriggerTimeOffset": 0.0,
          "EndTriggerTimeOffset": 0.0,
          "TriggerWeightThreshold": 1E-05,
          "NotifyName": "Audio_Killer_Body_Shuffle_Low",
          "Notify": null,
          "NotifyStateClass": null,
          "Duration": 0.0,
          "EndLink": {
            "LinkedMontage": null,
            "SlotIndex": 0,
            "SegmentIndex": -1,
            "LinkMethod": "EAnimLinkMethod::Absolute",
            "CachedLinkMethod": "EAnimLinkMethod::Absolute",
            "SegmentBeginTime": 0.0,
            "SegmentLength": 0.0,
            "LinkValue": 1.7370796,
            "LinkedSequence": null
          },
          "bConvertedFromBranchingPoint": false,
          "MontageTickType": "EMontageNotifyTickType::Queued",
          "NotifyTriggerChance": 1.0,
          "NotifyFilterType": "ENotifyFilterType::NoFiltering",
          "NotifyFilterLOD": 0,
          "bTriggerOnDedicatedServer": true,
          "bTriggerOnFollower": false,
          "TrackIndex": 2,
          "LinkedMontage": null,
          "SlotIndex": 0,
          "SegmentIndex": 0,
          "LinkMethod": "EAnimLinkMethod::Absolute",
          "CachedLinkMethod": "EAnimLinkMethod::Absolute",
          "SegmentBeginTime": 0.0,
          "SegmentLength": 2.6666667,
          "LinkValue": 1.7370796,
          "LinkedSequence": {
            "ObjectName": "AnimSequence'GK_Grab_Obstacles_FT_FPV'",
            "ObjectPath": "DeadByDaylight/Content/Characters/Slashers/Guam/AnimSequences/Interactions/GK_Grab_Obstacles_FT_FPV.0"
          }
        },
        {
          "TriggerTimeOffset": 0.0,
          "EndTriggerTimeOffset": 0.0,
          "TriggerWeightThreshold": 1E-05,
          "NotifyName": "Audio_Killer_Walk_Footstep_Left",
          "Notify": null,
          "NotifyStateClass": null,
          "Duration": 0.0,
          "EndLink": {
            "LinkedMontage": null,
            "SlotIndex": 0,
            "SegmentIndex": -1,
            "LinkMethod": "EAnimLinkMethod::Absolute",
            "CachedLinkMethod": "EAnimLinkMethod::Absolute",
            "SegmentBeginTime": 0.0,
            "SegmentLength": 0.0,
            "LinkValue": 2.1895216,
            "LinkedSequence": null
          },
          "bConvertedFromBranchingPoint": false,
          "MontageTickType": "EMontageNotifyTickType::Queued",
          "NotifyTriggerChance": 1.0,
          "NotifyFilterType": "ENotifyFilterType::NoFiltering",
          "NotifyFilterLOD": 0,
          "bTriggerOnDedicatedServer": true,
          "bTriggerOnFollower": false,
          "TrackIndex": 1,
          "LinkedMontage": null,
          "SlotIndex": 0,
          "SegmentIndex": 0,
          "LinkMethod": "EAnimLinkMethod::Absolute",
          "CachedLinkMethod": "EAnimLinkMethod::Absolute",
          "SegmentBeginTime": 0.0,
          "SegmentLength": 2.6666667,
          "LinkValue": 2.1895216,
          "LinkedSequence": {
            "ObjectName": "AnimSequence'GK_Grab_Obstacles_FT_FPV'",
            "ObjectPath": "DeadByDaylight/Content/Characters/Slashers/Guam/AnimSequences/Interactions/GK_Grab_Obstacles_FT_FPV.0"
          }
        },
        {
          "TriggerTimeOffset": 0.0,
          "EndTriggerTimeOffset": 0.0,
          "TriggerWeightThreshold": 1E-05,
          "NotifyName": "Audio_Killer_Body_Shuffle_Low",
          "Notify": null,
          "NotifyStateClass": null,
          "Duration": 0.0,
          "EndLink": {
            "LinkedMontage": null,
            "SlotIndex": 0,
            "SegmentIndex": -1,
            "LinkMethod": "EAnimLinkMethod::Absolute",
            "CachedLinkMethod": "EAnimLinkMethod::Absolute",
            "SegmentBeginTime": 0.0,
            "SegmentLength": 0.0,
            "LinkValue": 2.1906378,
            "LinkedSequence": null
          },
          "bConvertedFromBranchingPoint": false,
          "MontageTickType": "EMontageNotifyTickType::Queued",
          "NotifyTriggerChance": 1.0,
          "NotifyFilterType": "ENotifyFilterType::NoFiltering",
          "NotifyFilterLOD": 0,
          "bTriggerOnDedicatedServer": true,
          "bTriggerOnFollower": false,
          "TrackIndex": 2,
          "LinkedMontage": null,
          "SlotIndex": 0,
          "SegmentIndex": 0,
          "LinkMethod": "EAnimLinkMethod::Absolute",
          "CachedLinkMethod": "EAnimLinkMethod::Absolute",
          "SegmentBeginTime": 0.0,
          "SegmentLength": 2.6666667,
          "LinkValue": 2.1906378,
          "LinkedSequence": {
            "ObjectName": "AnimSequence'GK_Grab_Obstacles_FT_FPV'",
            "ObjectPath": "DeadByDaylight/Content/Characters/Slashers/Guam/AnimSequences/Interactions/GK_Grab_Obstacles_FT_FPV.0"
          }
        }
      ],
      "SequenceLength": 2.6666667,
      "Skeleton": {
        "ObjectName": "Skeleton'SlasherMale_REF_Skeleton'",
        "ObjectPath": "DeadByDaylight/Content/Characters/Slashers/Models/SlasherMale_REF_Skeleton.444"
      }
    },
    "SkeletonGuid": "86D5005B-43A898D2-C21BD69E-C6FFC84C",
    "CompressedTrackToSkeletonMapTable": [
      0,
      1,
      47,
      71,
      72,
      73,
      74,
      184,
      48,
      49,
      50,
      51,
      185,
      2,
      3,
      4,
      5,
      126,
      127,
      94,
      95,
      96,
      97,
      98,
      99,
      100,
      117,
      118,
      119,
      112,
      113,
      114,
      107,
      108,
      109,
      102,
      103,
      104,
      122,
      123,
      124,
      186,
      6,
      159,
      160,
      128,
      129,
      130,
      131,
      132,
      133,
      134,
      151,
      152,
      153,
      146,
      147,
      148,
      141,
      142,
      143,
      136,
      137,
      138,
      455,
      456,
      457,
      458,
      158,
      157,
      187,
      7,
      8,
      9,
      16,
      17,
      30,
      33,
      34,
      459,
      460,
      461,
      462,
      463,
      464,
      465,
      466,
      467,
      468,
      469,
      470,
      471,
      472,
      473,
      474,
      10,
      475,
      476,
      477,
      478,
      31,
      37,
      40,
      479,
      480,
      481,
      482,
      483,
      484,
      485,
      486,
      453,
      454,
      452,
      171,
      176,
      177,
      172,
      173,
      174,
      175,
      179,
      178
    ],
    "CompressedCurveNames": [
      {
        "DisplayName": "ArmLT"
      },
      {
        "DisplayName": "ArmRT"
      },
      {
        "DisplayName": "BackStrap"
      },
      {
        "DisplayName": "Bucklet"
      },
      {
        "DisplayName": "Cam"
      },
      {
        "DisplayName": "CamOff"
      },
      {
        "DisplayName": "CamOffLT"
      },
      {
        "DisplayName": "CamperAttach"
      },
      {
        "DisplayName": "Elbow_RollLT"
      },
      {
        "DisplayName": "ElbowRollLT"
      },
      {
        "DisplayName": "FootRollLT"
      },
      {
        "DisplayName": "FrontStrap"
      },
      {
        "DisplayName": "HandRollLT"
      },
      {
        "DisplayName": "HandRollRT"
      },
      {
        "DisplayName": "Head"
      },
      {
        "DisplayName": "hipOffsetTY"
      },
      {
        "DisplayName": "hipOffsetTZ"
      },
      {
        "DisplayName": "HookClav"
      },
      {
        "DisplayName": "HookSkinNeck"
      },
      {
        "DisplayName": "HookSkinNeckLT"
      },
      {
        "DisplayName": "HookSkinNeckOff"
      },
      {
        "DisplayName": "KneeRollLT"
      },
      {
        "DisplayName": "KneeRollRT"
      },
      {
        "DisplayName": "LegLT"
      },
      {
        "DisplayName": "LegRT"
      },
      {
        "DisplayName": "Neck"
      },
      {
        "DisplayName": "ShoulderRollLT"
      },
      {
        "DisplayName": "ShoulderRollOffLT"
      },
      {
        "DisplayName": "ShoulderRollOffRT"
      },
      {
        "DisplayName": "ShoulderRollRT"
      },
      {
        "DisplayName": "Tail"
      },
      {
        "DisplayName": "Torso"
      }
    ],
    "CompressedCurveData": {
      "FloatCurves": [
        {
          "FloatCurve": {
            "Keys": [
              {
                "InterpMode": "RCIM_Linear",
                "TangentMode": "RCTM_Auto",
                "TangentWeightMode": "RCTWM_WeightedNone",
                "Time": 0.0,
                "Value": 3.0,
                "ArriveTangent": 0.0,
                "ArriveTangentWeight": 0.0,
                "LeaveTangent": 0.0,
                "LeaveTangentWeight": 0.0
              }
            ],
            "DefaultValue": 3.4028235E+38,
            "PreInfinityExtrap": "RCCE_Constant",
            "PostInfinityExtrap": "RCCE_Constant"
          },
          "Name": {
            "DisplayName": "ArmLT"
          },
          "CurveTypeFlags": 4
        },
        {
          "FloatCurve": {
            "Keys": [
              {
                "InterpMode": "RCIM_Linear",
                "TangentMode": "RCTM_Auto",
                "TangentWeightMode": "RCTWM_WeightedNone",
                "Time": 0.0,
                "Value": 3.0,
                "ArriveTangent": 0.0,
                "ArriveTangentWeight": 0.0,
                "LeaveTangent": 0.0,
                "LeaveTangentWeight": 0.0
              }
            ],
            "DefaultValue": 3.4028235E+38,
            "PreInfinityExtrap": "RCCE_Constant",
            "PostInfinityExtrap": "RCCE_Constant"
          },
          "Name": {
            "DisplayName": "ArmRT"
          },
          "CurveTypeFlags": 4
        },
        {
          "FloatCurve": {
            "Keys": [
              {
                "InterpMode": "RCIM_Linear",
                "TangentMode": "RCTM_Auto",
                "TangentWeightMode": "RCTWM_WeightedNone",
                "Time": 0.0,
                "Value": 2.0,
                "ArriveTangent": 0.0,
                "ArriveTangentWeight": 0.0,
                "LeaveTangent": 0.0,
                "LeaveTangentWeight": 0.0
              }
            ],
            "DefaultValue": 3.4028235E+38,
            "PreInfinityExtrap": "RCCE_Constant",
            "PostInfinityExtrap": "RCCE_Constant"
          },
          "Name": {
            "DisplayName": "BackStrap"
          },
          "CurveTypeFlags": 4
        },
        {
          "FloatCurve": {
            "Keys": [
              {
                "InterpMode": "RCIM_Linear",
                "TangentMode": "RCTM_Auto",
                "TangentWeightMode": "RCTWM_WeightedNone",
                "Time": 0.0,
                "Value": 2.0,
                "ArriveTangent": 0.0,
                "ArriveTangentWeight": 0.0,
                "LeaveTangent": 0.0,
                "LeaveTangentWeight": 0.0
              }
            ],
            "DefaultValue": 3.4028235E+38,
            "PreInfinityExtrap": "RCCE_Constant",
            "PostInfinityExtrap": "RCCE_Constant"
          },
          "Name": {
            "DisplayName": "Bucklet"
          },
          "CurveTypeFlags": 4
        },
        {
          "FloatCurve": {
            "Keys": [
              {
                "InterpMode": "RCIM_Linear",
                "TangentMode": "RCTM_Auto",
                "TangentWeightMode": "RCTWM_WeightedNone",
                "Time": 0.0,
                "Value": 2.0,
                "ArriveTangent": 0.0,
                "ArriveTangentWeight": 0.0,
                "LeaveTangent": 0.0,
                "LeaveTangentWeight": 0.0
              }
            ],
            "DefaultValue": 3.4028235E+38,
            "PreInfinityExtrap": "RCCE_Constant",
            "PostInfinityExtrap": "RCCE_Constant"
          },
          "Name": {
            "DisplayName": "Cam"
          },
          "CurveTypeFlags": 4
        },
        {
          "FloatCurve": {
            "Keys": [
              {
                "InterpMode": "RCIM_Linear",
                "TangentMode": "RCTM_Auto",
                "TangentWeightMode": "RCTWM_WeightedNone",
                "Time": 0.0,
                "Value": 2.0,
                "ArriveTangent": 0.0,
                "ArriveTangentWeight": 0.0,
                "LeaveTangent": 0.0,
                "LeaveTangentWeight": 0.0
              }
            ],
            "DefaultValue": 3.4028235E+38,
            "PreInfinityExtrap": "RCCE_Constant",
            "PostInfinityExtrap": "RCCE_Constant"
          },
          "Name": {
            "DisplayName": "CamOff"
          },
          "CurveTypeFlags": 4
        },
        {
          "FloatCurve": {
            "Keys": [
              {
                "InterpMode": "RCIM_Linear",
                "TangentMode": "RCTM_Auto",
                "TangentWeightMode": "RCTWM_WeightedNone",
                "Time": 0.0,
                "Value": 2.0,
                "ArriveTangent": 0.0,
                "ArriveTangentWeight": 0.0,
                "LeaveTangent": 0.0,
                "LeaveTangentWeight": 0.0
              }
            ],
            "DefaultValue": 3.4028235E+38,
            "PreInfinityExtrap": "RCCE_Constant",
            "PostInfinityExtrap": "RCCE_Constant"
          },
          "Name": {
            "DisplayName": "CamOffLT"
          },
          "CurveTypeFlags": 4
        },
        {
          "FloatCurve": {
            "Keys": [
              {
                "InterpMode": "RCIM_Linear",
                "TangentMode": "RCTM_Auto",
                "TangentWeightMode": "RCTWM_WeightedNone",
                "Time": 0.0,
                "Value": 2.0,
                "ArriveTangent": 0.0,
                "ArriveTangentWeight": 0.0,
                "LeaveTangent": 0.0,
                "LeaveTangentWeight": 0.0
              }
            ],
            "DefaultValue": 3.4028235E+38,
            "PreInfinityExtrap": "RCCE_Constant",
            "PostInfinityExtrap": "RCCE_Constant"
          },
          "Name": {
            "DisplayName": "CamperAttach"
          },
          "CurveTypeFlags": 4
        },
        {
          "FloatCurve": {
            "Keys": [
              {
                "InterpMode": "RCIM_Linear",
                "TangentMode": "RCTM_Auto",
                "TangentWeightMode": "RCTWM_WeightedNone",
                "Time": 0.0,
                "Value": 2.0,
                "ArriveTangent": 0.0,
                "ArriveTangentWeight": 0.0,
                "LeaveTangent": 0.0,
                "LeaveTangentWeight": 0.0
              }
            ],
            "DefaultValue": 3.4028235E+38,
            "PreInfinityExtrap": "RCCE_Constant",
            "PostInfinityExtrap": "RCCE_Constant"
          },
          "Name": {
            "DisplayName": "Elbow_RollLT"
          },
          "CurveTypeFlags": 4
        },
        {
          "FloatCurve": {
            "Keys": [
              {
                "InterpMode": "RCIM_Linear",
                "TangentMode": "RCTM_Auto",
                "TangentWeightMode": "RCTWM_WeightedNone",
                "Time": 0.0,
                "Value": 2.0,
                "ArriveTangent": 0.0,
                "ArriveTangentWeight": 0.0,
                "LeaveTangent": 0.0,
                "LeaveTangentWeight": 0.0
              }
            ],
            "DefaultValue": 3.4028235E+38,
            "PreInfinityExtrap": "RCCE_Constant",
            "PostInfinityExtrap": "RCCE_Constant"
          },
          "Name": {
            "DisplayName": "ElbowRollLT"
          },
          "CurveTypeFlags": 4
        },
        {
          "FloatCurve": {
            "Keys": [
              {
                "InterpMode": "RCIM_Linear",
                "TangentMode": "RCTM_Auto",
                "TangentWeightMode": "RCTWM_WeightedNone",
                "Time": 0.0,
                "Value": 3.0,
                "ArriveTangent": 0.0,
                "ArriveTangentWeight": 0.0,
                "LeaveTangent": 0.0,
                "LeaveTangentWeight": 0.0
              }
            ],
            "DefaultValue": 3.4028235E+38,
            "PreInfinityExtrap": "RCCE_Constant",
            "PostInfinityExtrap": "RCCE_Constant"
          },
          "Name": {
            "DisplayName": "FootRollLT"
          },
          "CurveTypeFlags": 4
        },
        {
          "FloatCurve": {
            "Keys": [
              {
                "InterpMode": "RCIM_Linear",
                "TangentMode": "RCTM_Auto",
                "TangentWeightMode": "RCTWM_WeightedNone",
                "Time": 0.0,
                "Value": 3.0,
                "ArriveTangent": 0.0,
                "ArriveTangentWeight": 0.0,
                "LeaveTangent": 0.0,
                "LeaveTangentWeight": 0.0
              }
            ],
            "DefaultValue": 3.4028235E+38,
            "PreInfinityExtrap": "RCCE_Constant",
            "PostInfinityExtrap": "RCCE_Constant"
          },
          "Name": {
            "DisplayName": "FrontStrap"
          },
          "CurveTypeFlags": 4
        },
        {
          "FloatCurve": {
            "Keys": [
              {
                "InterpMode": "RCIM_Linear",
                "TangentMode": "RCTM_Auto",
                "TangentWeightMode": "RCTWM_WeightedNone",
                "Time": 0.0,
                "Value": 3.0,
                "ArriveTangent": 0.0,
                "ArriveTangentWeight": 0.0,
                "LeaveTangent": 0.0,
                "LeaveTangentWeight": 0.0
              }
            ],
            "DefaultValue": 3.4028235E+38,
            "PreInfinityExtrap": "RCCE_Constant",
            "PostInfinityExtrap": "RCCE_Constant"
          },
          "Name": {
            "DisplayName": "HandRollLT"
          },
          "CurveTypeFlags": 4
        },
        {
          "FloatCurve": {
            "Keys": [
              {
                "InterpMode": "RCIM_Linear",
                "TangentMode": "RCTM_Auto",
                "TangentWeightMode": "RCTWM_WeightedNone",
                "Time": 0.0,
                "Value": 3.0,
                "ArriveTangent": 0.0,
                "ArriveTangentWeight": 0.0,
                "LeaveTangent": 0.0,
                "LeaveTangentWeight": 0.0
              }
            ],
            "DefaultValue": 3.4028235E+38,
            "PreInfinityExtrap": "RCCE_Constant",
            "PostInfinityExtrap": "RCCE_Constant"
          },
          "Name": {
            "DisplayName": "HandRollRT"
          },
          "CurveTypeFlags": 4
        },
        {
          "FloatCurve": {
            "Keys": [
              {
                "InterpMode": "RCIM_Linear",
                "TangentMode": "RCTM_Auto",
                "TangentWeightMode": "RCTWM_WeightedNone",
                "Time": 0.0,
                "Value": 2.0,
                "ArriveTangent": 0.0,
                "ArriveTangentWeight": 0.0,
                "LeaveTangent": 0.0,
                "LeaveTangentWeight": 0.0
              }
            ],
            "DefaultValue": 3.4028235E+38,
            "PreInfinityExtrap": "RCCE_Constant",
            "PostInfinityExtrap": "RCCE_Constant"
          },
          "Name": {
            "DisplayName": "Head"
          },
          "CurveTypeFlags": 4
        },
        {
          "FloatCurve": {
            "Keys": [
              {
                "InterpMode": "RCIM_Cubic",
                "TangentMode": "RCTM_Auto",
                "TangentWeightMode": "RCTWM_WeightedNone",
                "Time": 0.0,
                "Value": -1.147718,
                "ArriveTangent": 0.0060582156,
                "ArriveTangentWeight": 0.0,
                "LeaveTangent": 0.0060582156,
                "LeaveTangentWeight": 0.0
              },
              {
                "InterpMode": "RCIM_Cubic",
                "TangentMode": "RCTM_Auto",
                "TangentWeightMode": "RCTWM_WeightedNone",
                "Time": 0.033333335,
                "Value": -1.147516,
                "ArriveTangent": 0.00655353,
                "ArriveTangentWeight": 0.0,
                "LeaveTangent": 0.00655353,
                "LeaveTangentWeight": 0.0
              },
              {
                "InterpMode": "RCIM_Cubic",
                "TangentMode": "RCTM_Auto",
                "TangentWeightMode": "RCTWM_WeightedNone",
                "Time": 0.06666667,
                "Value": -1.147281,
                "ArriveTangent": 0.0075459485,
                "ArriveTangentWeight": 0.0,
                "LeaveTangent": 0.0075459485,
                "LeaveTangentWeight": 0.0
              },
              {
                "InterpMode": "RCIM_Cubic",
                "TangentMode": "RCTM_Auto",
                "TangentWeightMode": "RCTWM_WeightedNone",
                "Time": 0.1,
                "Value": -1.147013,
                "ArriveTangent": 0.008520484,
                "ArriveTangentWeight": 0.0,
                "LeaveTangent": 0.008520484,
                "LeaveTangentWeight": 0.0
              },
              {
                "InterpMode": "RCIM_Cubic",
                "TangentMode": "RCTM_Auto",
                "TangentWeightMode": "RCTWM_WeightedNone",
                "Time": 0.13333334,
                "Value": -1.146713,
                "ArriveTangent": 0.009464621,
                "ArriveTangentWeight": 0.0,
                "LeaveTangent": 0.009464621,
                "LeaveTangentWeight": 0.0
              },
              {
                "InterpMode": "RCIM_Cubic",
                "TangentMode": "RCTM_Auto",
                "TangentWeightMode": "RCTWM_WeightedNone",
                "Time": 0.16666667,
                "Value": -1.146382,
                "ArriveTangent": 0.010365845,
                "ArriveTangentWeight": 0.0,
                "LeaveTangent": 0.010365845,
                "LeaveTangentWeight": 0.0
              },
              {
                "InterpMode": "RCIM_Cubic",
                "TangentMode": "RCTM_Auto",
                "TangentWeightMode": "RCTWM_WeightedNone",
                "Time": 0.2,
                "Value": -1.146022,
                "ArriveTangent": 0.011249186,
                "ArriveTangentWeight": 0.0,
                "LeaveTangent": 0.011249186,
                "LeaveTangentWeight": 0.0
              },
              {
                "InterpMode": "RCIM_Cubic",
                "TangentMode": "RCTM_Auto",
                "TangentWeightMode": "RCTWM_WeightedNone",
                "Time": 0.23333333,
                "Value": -1.145632,
                "ArriveTangent": 0.012509822,
                "ArriveTangentWeight": 0.0,
                "LeaveTangent": 0.012509822,
                "LeaveTangentWeight": 0.0
              },
              {
                "InterpMode": "RCIM_Cubic",
                "TangentMode": "RCTM_Auto",
                "TangentWeightMode": "RCTWM_WeightedNone",
                "Time": 0.3,
                "Value": -1.144771,
                "ArriveTangent": 0.013320445,
                "ArriveTangentWeight": 0.0,
                "LeaveTangent": 0.013320445,
                "LeaveTangentWeight": 0.0
              },
              {
                "InterpMode": "RCIM_Cubic",
                "TangentMode": "RCTM_Auto",
                "TangentWeightMode": "RCTWM_WeightedNone",
                "Time": 0.33333334,
                "Value": -1.1443,
                "ArriveTangent": 0.014489294,
                "ArriveTangentWeight": 0.0,
                "LeaveTangent": 0.014489294,
                "LeaveTangentWeight": 0.0
              },
              {
                "InterpMode": "RCIM_Cubic",
                "TangentMode": "RCTM_Auto",
                "TangentWeightMode": "RCTWM_WeightedNone",
                "Time": 0.36666667,
                "Value": -1.143805,
                "ArriveTangent": 0.015224219,
                "ArriveTangentWeight": 0.0,
                "LeaveTangent": 0.015224219,
                "LeaveTangentWeight": 0.0
              },
              {
                "InterpMode": "RCIM_Cubic",
                "TangentMode": "RCTM_Auto",
                "TangentWeightMode": "RCTWM_WeightedNone",
                "Time": 0.4,
                "Value": -1.143285,
                "ArriveTangent": 0.01594484,
                "ArriveTangentWeight": 0.0,
                "LeaveTangent": 0.01594484,
                "LeaveTangentWeight": 0.0
              },
              {
                "InterpMode": "RCIM_Cubic",
                "TangentMode": "RCTM_Auto",
                "TangentWeightMode": "RCTWM_WeightedNone",
                "Time": 0.43333334,
                "Value": -1.142742,
                "ArriveTangent": 0.016620757,
                "ArriveTangentWeight": 0.0,
                "LeaveTangent": 0.016620757,
                "LeaveTangentWeight": 0.0
              },
              {
                "InterpMode": "RCIM_Cubic",
                "TangentMode": "RCTM_Auto",
                "TangentWeightMode": "RCTWM_WeightedNone",
                "Time": 0.46666667,
                "Value": -1.142177,
                "ArriveTangent": 0.01728058,
                "ArriveTangentWeight": 0.0,
                "LeaveTangent": 0.01728058,
                "LeaveTangentWeight": 0.0
              },
              {
                "InterpMode": "RCIM_Cubic",
                "TangentMode": "RCTM_Auto",
                "TangentWeightMode": "RCTWM_WeightedNone",
                "Time": 0.5,
                "Value": -1.14159,
                "ArriveTangent": 0.017893903,
                "ArriveTangentWeight": 0.0,
                "LeaveTangent": 0.017893903,
                "LeaveTangentWeight": 0.0
              },
              {
                "InterpMode": "RCIM_Cubic",
                "TangentMode": "RCTM_Auto",
                "TangentWeightMode": "RCTWM_WeightedNone",
                "Time": 0.53333336,
                "Value": -1.140984,
                "ArriveTangent": 0.018494727,
                "ArriveTangentWeight": 0.0,
                "LeaveTangent": 0.018494727,
                "LeaveTangentWeight": 0.0
              },
              {
                "InterpMode": "RCIM_Cubic",
                "TangentMode": "RCTM_Auto",
                "TangentWeightMode": "RCTWM_WeightedNone",
                "Time": 0.56666666,
                "Value": -1.140357,
                "ArriveTangent": 0.019065144,
                "ArriveTangentWeight": 0.0,
                "LeaveTangent": 0.019065144,
                "LeaveTangentWeight": 0.0
              },
              {
                "InterpMode": "RCIM_Cubic",
                "TangentMode": "RCTM_Auto",
                "TangentWeightMode": "RCTWM_WeightedNone",
                "Time": 0.6,
                "Value": -1.139713,
                "ArriveTangent": 0.019605162,
                "ArriveTangentWeight": 0.0,
                "LeaveTangent": 0.019605162,
                "LeaveTangentWeight": 0.0
              },
              {
                "InterpMode": "RCIM_Cubic",
                "TangentMode": "RCTM_Auto",
                "TangentWeightMode": "RCTWM_WeightedNone",
                "Time": 0.6333333,
                "Value": -1.13905,
                "ArriveTangent": 0.02011657,
                "ArriveTangentWeight": 0.0,
                "LeaveTangent": 0.02011657,
                "LeaveTangentWeight": 0.0
              },
              {
                "InterpMode": "RCIM_Cubic",
                "TangentMode": "RCTM_Auto",
                "TangentWeightMode": "RCTWM_WeightedNone",
                "Time": 0.6666667,
                "Value": -1.138372,
                "ArriveTangent": 0.02059579,
                "ArriveTangentWeight": 0.0,
                "LeaveTangent": 0.02059579,
                "LeaveTangentWeight": 0.0
              },
              {
                "InterpMode": "RCIM_Cubic",
                "TangentMode": "RCTM_Auto",
                "TangentWeightMode": "RCTWM_WeightedNone",
                "Time": 0.7,
                "Value": -1.137677,
                "ArriveTangent": 0.021058919,
                "ArriveTangentWeight": 0.0,
                "LeaveTangent": 0.021058919,
                "LeaveTangentWeight": 0.0
              },
              {
                "InterpMode": "RCIM_Cubic",
                "TangentMode": "RCTM_Auto",
                "TangentWeightMode": "RCTWM_WeightedNone",
                "Time": 0.73333335,
                "Value": -1.136968,
                "ArriveTangent": 0.021679396,
                "ArriveTangentWeight": 0.0,
                "LeaveTangent": 0.021679396,
                "LeaveTangentWeight": 0.0
              },
              {
                "InterpMode": "RCIM_Cubic",
                "TangentMode": "RCTM_Auto",
                "TangentWeightMode": "RCTWM_WeightedNone",
                "Time": 0.8,
                "Value": -1.135509,
                "ArriveTangent": 0.02223015,
                "ArriveTangentWeight": 0.0,
                "LeaveTangent": 0.02223015,
                "LeaveTangentWeight": 0.0
              },
              {
                "InterpMode": "RCIM_Cubic",
                "TangentMode": "RCTM_Auto",
                "TangentWeightMode": "RCTWM_WeightedNone",
                "Time": 0.8666667,
                "Value": -1.134004,
                "ArriveTangent": 0.022740372,
                "ArriveTangentWeight": 0.0,
                "LeaveTangent": 0.022740372,
                "LeaveTangentWeight": 0.0
              },
              {
                "InterpMode": "RCIM_Cubic",
                "TangentMode": "RCTM_Auto",
                "TangentWeightMode": "RCTWM_WeightedNone",
                "Time": 0.9,
                "Value": -1.133235,
                "ArriveTangent": 0.023190381,
                "ArriveTangentWeight": 0.0,
                "LeaveTangent": 0.023190381,
                "LeaveTangentWeight": 0.0
              },
              {
                "InterpMode": "RCIM_Cubic",
                "TangentMode": "RCTM_Auto",
                "TangentWeightMode": "RCTWM_WeightedNone",
                "Time": 0.93333334,
                "Value": -1.132458,
                "ArriveTangent": 0.023429992,
                "ArriveTangentWeight": 0.0,
                "LeaveTangent": 0.023429992,
                "LeaveTangentWeight": 0.0
              },
              {
                "InterpMode": "RCIM_Cubic",
                "TangentMode": "RCTM_Auto",
                "TangentWeightMode": "RCTWM_WeightedNone",
                "Time": 0.96666664,
                "Value": -1.131673,
                "ArriveTangent": 0.023850193,
                "ArriveTangentWeight": 0.0,
                "LeaveTangent": 0.023850193,
                "LeaveTangentWeight": 0.0
              },
              {
                "InterpMode": "RCIM_Cubic",
                "TangentMode": "RCTM_Auto",
                "TangentWeightMode": "RCTWM_WeightedNone",
                "Time": 1.0666667,
                "Value": -1.129278,
                "ArriveTangent": 0.024029901,
                "ArriveTangentWeight": 0.0,
                "LeaveTangent": 0.024029901,
                "LeaveTangentWeight": 0.0
              },
              {
                "InterpMode": "RCIM_Cubic",
                "TangentMode": "RCTM_Auto",
                "TangentWeightMode": "RCTWM_WeightedNone",
                "Time": 1.1,
                "Value": -1.128469,
                "ArriveTangent": 0.024299048,
                "ArriveTangentWeight": 0.0,
                "LeaveTangent": 0.024299048,
                "LeaveTangentWeight": 0.0
              },
              {
                "InterpMode": "RCIM_Cubic",
                "TangentMode": "RCTM_Auto",
                "TangentWeightMode": "RCTWM_WeightedNone",
                "Time": 1.1333333,
                "Value": -1.127658,
                "ArriveTangent": 0.02437415,
                "ArriveTangentWeight": 0.0,
                "LeaveTangent": 0.02437415,
                "LeaveTangentWeight": 0.0
              },
              {
                "InterpMode": "RCIM_Cubic",
                "TangentMode": "RCTM_Auto",
                "TangentWeightMode": "RCTWM_WeightedNone",
                "Time": 1.1666666,
                "Value": -1.126844,
                "ArriveTangent": 0.024434904,
                "ArriveTangentWeight": 0.0,
                "LeaveTangent": 0.024434904,
                "LeaveTangentWeight": 0.0
              },
              {
                "InterpMode": "RCIM_Cubic",
                "TangentMode": "RCTM_Auto",
                "TangentWeightMode": "RCTWM_WeightedNone",
                "Time": 1.2,
                "Value": -1.126029,
                "ArriveTangent": 0.024465302,
                "ArriveTangentWeight": 0.0,
                "LeaveTangent": 0.024465302,
                "LeaveTangentWeight": 0.0
              },
              {
                "InterpMode": "RCIM_Cubic",
                "TangentMode": "RCTM_Auto",
                "TangentWeightMode": "RCTWM_WeightedNone",
                "Time": 1.2333333,
                "Value": -1.125213,
                "ArriveTangent": 0.024465347,
                "ArriveTangentWeight": 0.0,
                "LeaveTangent": 0.024465347,
                "LeaveTangentWeight": 0.0
              },
              {
                "InterpMode": "RCIM_Cubic",
                "TangentMode": "RCTM_Auto",
                "TangentWeightMode": "RCTWM_WeightedNone",
                "Time": 1.2666667,
                "Value": -1.124398,
                "ArriveTangent": 0.024434948,
                "ArriveTangentWeight": 0.0,
                "LeaveTangent": 0.024434948,
                "LeaveTangentWeight": 0.0
              },
              {
                "InterpMode": "RCIM_Cubic",
                "TangentMode": "RCTM_Auto",
                "TangentWeightMode": "RCTWM_WeightedNone",
                "Time": 1.3,
                "Value": -1.123584,
                "ArriveTangent": 0.024374107,
                "ArriveTangentWeight": 0.0,
                "LeaveTangent": 0.024374107,
                "LeaveTangentWeight": 0.0
              },
              {
                "InterpMode": "RCIM_Cubic",
                "TangentMode": "RCTM_Auto",
                "TangentWeightMode": "RCTWM_WeightedNone",
                "Time": 1.3333334,
                "Value": -1.122773,
                "ArriveTangent": 0.024230475,
                "ArriveTangentWeight": 0.0,
                "LeaveTangent": 0.024230475,
                "LeaveTangentWeight": 0.0
              },
              {
                "InterpMode": "RCIM_Cubic",
                "TangentMode": "RCTM_Auto",
                "TangentWeightMode": "RCTWM_WeightedNone",
                "Time": 1.4,
                "Value": -1.121161,
                "ArriveTangent": 0.024110101,
                "ArriveTangentWeight": 0.0,
                "LeaveTangent": 0.024110101,
                "LeaveTangentWeight": 0.0
              },
              {
                "InterpMode": "RCIM_Cubic",
                "TangentMode": "RCTM_Auto",
                "TangentWeightMode": "RCTWM_WeightedNone",
                "Time": 1.4333333,
                "Value": -1.120362,
                "ArriveTangent": 0.023864487,
                "ArriveTangentWeight": 0.0,
                "LeaveTangent": 0.023864487,
                "LeaveTangentWeight": 0.0
              },
              {
                "InterpMode": "RCIM_Cubic",
                "TangentMode": "RCTM_Auto",
                "TangentWeightMode": "RCTWM_WeightedNone",
                "Time": 1.4666667,
                "Value": -1.11957,
                "ArriveTangent": 0.023671368,
                "ArriveTangentWeight": 0.0,
                "LeaveTangent": 0.023671368,
                "LeaveTangentWeight": 0.0
              },
              {
                "InterpMode": "RCIM_Cubic",
                "TangentMode": "RCTM_Auto",
                "TangentWeightMode": "RCTWM_WeightedNone",
                "Time": 1.5,
                "Value": -1.118784,
                "ArriveTangent": 0.023310179,
                "ArriveTangentWeight": 0.0,
                "LeaveTangent": 0.023310179,
                "LeaveTangentWeight": 0.0
              },
              {
                "InterpMode": "RCIM_Cubic",
                "TangentMode": "RCTM_Auto",
                "TangentWeightMode": "RCTWM_WeightedNone",
                "Time": 1.5666667,
                "Value": -1.117239,
                "ArriveTangent": 0.023039574,
                "ArriveTangentWeight": 0.0,
                "LeaveTangent": 0.023039574,
                "LeaveTangentWeight": 0.0
              },
              {
                "InterpMode": "RCIM_Cubic",
                "TangentMode": "RCTM_Auto",
                "TangentWeightMode": "RCTWM_WeightedNone",
                "Time": 1.6,
                "Value": -1.11648,
                "ArriveTangent": 0.022589587,
                "ArriveTangentWeight": 0.0,
                "LeaveTangent": 0.022589587,
                "LeaveTangentWeight": 0.0
              },
              {
                "InterpMode": "RCIM_Cubic",
                "TangentMode": "RCTM_Auto",
                "TangentWeightMode": "RCTWM_WeightedNone",
                "Time": 1.6333333,
                "Value": -1.115733,
                "ArriveTangent": 0.022244474,
                "ArriveTangentWeight": 0.0,
                "LeaveTangent": 0.022244474,
                "LeaveTangentWeight": 0.0
              },
              {
                "InterpMode": "RCIM_Cubic",
                "TangentMode": "RCTM_Auto",
                "TangentWeightMode": "RCTWM_WeightedNone",
                "Time": 1.6666666,
                "Value": -1.114997,
                "ArriveTangent": 0.021885019,
                "ArriveTangentWeight": 0.0,
                "LeaveTangent": 0.021885019,
                "LeaveTangentWeight": 0.0
              },
              {
                "InterpMode": "RCIM_Cubic",
                "TangentMode": "RCTM_Auto",
                "TangentWeightMode": "RCTWM_WeightedNone",
                "Time": 1.7,
                "Value": -1.114274,
                "ArriveTangent": 0.0214809,
                "ArriveTangentWeight": 0.0,
                "LeaveTangent": 0.0214809,
                "LeaveTangentWeight": 0.0
              },
              {
                "InterpMode": "RCIM_Cubic",
                "TangentMode": "RCTM_Auto",
                "TangentWeightMode": "RCTWM_WeightedNone",
                "Time": 1.7333333,
                "Value": -1.113565,
                "ArriveTangent": 0.021044632,
                "ArriveTangentWeight": 0.0,
                "LeaveTangent": 0.021044632,
                "LeaveTangentWeight": 0.0
              },
              {
                "InterpMode": "RCIM_Cubic",
                "TangentMode": "RCTM_Auto",
                "TangentWeightMode": "RCTWM_WeightedNone",
                "Time": 1.7666667,
                "Value": -1.112871,
                "ArriveTangent": 0.020594021,
                "ArriveTangentWeight": 0.0,
                "LeaveTangent": 0.020594021,
                "LeaveTangentWeight": 0.0
              },
              {
                "InterpMode": "RCIM_Cubic",
                "TangentMode": "RCTM_Auto",
                "TangentWeightMode": "RCTWM_WeightedNone",
                "Time": 1.8,
                "Value": -1.112192,
                "ArriveTangent": 0.020130856,
                "ArriveTangentWeight": 0.0,
                "LeaveTangent": 0.020130856,
                "LeaveTangentWeight": 0.0
              },
              {
                "InterpMode": "RCIM_Cubic",
                "TangentMode": "RCTM_Auto",
                "TangentWeightMode": "RCTWM_WeightedNone",
                "Time": 1.8333334,
                "Value": -1.111529,
                "ArriveTangent": 0.019605143,
                "ArriveTangentWeight": 0.0,
                "LeaveTangent": 0.019605143,
                "LeaveTangentWeight": 0.0
              },
              {
                "InterpMode": "RCIM_Cubic",
                "TangentMode": "RCTM_Auto",
                "TangentWeightMode": "RCTWM_WeightedNone",
                "Time": 1.8666667,
                "Value": -1.110885,
                "ArriveTangent": 0.01906516,
                "ArriveTangentWeight": 0.0,
                "LeaveTangent": 0.01906516,
                "LeaveTangentWeight": 0.0
              },
              {
                "InterpMode": "RCIM_Cubic",
                "TangentMode": "RCTM_Auto",
                "TangentWeightMode": "RCTWM_WeightedNone",
                "Time": 1.9,
                "Value": -1.110258,
                "ArriveTangent": 0.018494742,
                "ArriveTangentWeight": 0.0,
                "LeaveTangent": 0.018494742,
                "LeaveTangentWeight": 0.0
              },
              {
                "InterpMode": "RCIM_Cubic",
                "TangentMode": "RCTM_Auto",
                "TangentWeightMode": "RCTWM_WeightedNone",
                "Time": 1.9333333,
                "Value": -1.109652,
                "ArriveTangent": 0.017893896,
                "ArriveTangentWeight": 0.0,
                "LeaveTangent": 0.017893896,
                "LeaveTangentWeight": 0.0
              },
              {
                "InterpMode": "RCIM_Cubic",
                "TangentMode": "RCTM_Auto",
                "TangentWeightMode": "RCTWM_WeightedNone",
                "Time": 1.9666667,
                "Value": -1.109065,
                "ArriveTangent": 0.016950365,
                "ArriveTangentWeight": 0.0,
                "LeaveTangent": 0.016950365,
                "LeaveTangentWeight": 0.0
              },
              {
                "InterpMode": "RCIM_Cubic",
                "TangentMode": "RCTM_Auto",
                "TangentWeightMode": "RCTWM_WeightedNone",
                "Time": 2.0333333,
                "Value": -1.107957,
                "ArriveTangent": 0.016280428,
                "ArriveTangentWeight": 0.0,
                "LeaveTangent": 0.016280428,
                "LeaveTangentWeight": 0.0
              },
              {
                "InterpMode": "RCIM_Cubic",
                "TangentMode": "RCTM_Auto",
                "TangentWeightMode": "RCTWM_WeightedNone",
                "Time": 2.0666666,
                "Value": -1.107437,
                "ArriveTangent": 0.01484988,
                "ArriveTangentWeight": 0.0,
                "LeaveTangent": 0.01484988,
                "LeaveTangentWeight": 0.0
              },
              {
                "InterpMode": "RCIM_Cubic",
                "TangentMode": "RCTM_Auto",
                "TangentWeightMode": "RCTWM_WeightedNone",
                "Time": 2.1333334,
                "Value": -1.106472,
                "ArriveTangent": 0.014100054,
                "ArriveTangentWeight": 0.0,
                "LeaveTangent": 0.014100054,
                "LeaveTangentWeight": 0.0
              },
              {
                "InterpMode": "RCIM_Cubic",
                "TangentMode": "RCTM_Auto",
                "TangentWeightMode": "RCTWM_WeightedNone",
                "Time": 2.1666667,
                "Value": -1.106027,
                "ArriveTangent": 0.012930048,
                "ArriveTangentWeight": 0.0,
                "LeaveTangent": 0.012930048,
                "LeaveTangentWeight": 0.0
              },
              {
                "InterpMode": "RCIM_Cubic",
                "TangentMode": "RCTM_Auto",
                "TangentWeightMode": "RCTWM_WeightedNone",
                "Time": 2.2,
                "Value": -1.10561,
                "ArriveTangent": 0.0121057145,
                "ArriveTangentWeight": 0.0,
                "LeaveTangent": 0.0121057145,
                "LeaveTangentWeight": 0.0
              },
              {
                "InterpMode": "RCIM_Cubic",
                "TangentMode": "RCTM_Auto",
                "TangentWeightMode": "RCTWM_WeightedNone",
                "Time": 2.2333333,
                "Value": -1.10522,
                "ArriveTangent": 0.011250984,
                "ArriveTangentWeight": 0.0,
                "LeaveTangent": 0.011250984,
                "LeaveTangentWeight": 0.0
              },
              {
                "InterpMode": "RCIM_Cubic",
                "TangentMode": "RCTM_Auto",
                "TangentWeightMode": "RCTWM_WeightedNone",
                "Time": 2.2666667,
                "Value": -1.10486,
                "ArriveTangent": 0.009442279,
                "ArriveTangentWeight": 0.0,
                "LeaveTangent": 0.009442279,
                "LeaveTangentWeight": 0.0
              },
              {
                "InterpMode": "RCIM_Cubic",
                "TangentMode": "RCTM_Auto",
                "TangentWeightMode": "RCTWM_WeightedNone",
                "Time": 2.3666666,
                "Value": -1.103961,
                "ArriveTangent": 0.008504383,
                "ArriveTangentWeight": 0.0,
                "LeaveTangent": 0.008504383,
                "LeaveTangentWeight": 0.0
              },
              {
                "InterpMode": "RCIM_Cubic",
                "TangentMode": "RCTM_Auto",
                "TangentWeightMode": "RCTWM_WeightedNone",
                "Time": 2.4,
                "Value": -1.103726,
                "ArriveTangent": 0.0065553016,
                "ArriveTangentWeight": 0.0,
                "LeaveTangent": 0.0065553016,
                "LeaveTangentWeight": 0.0
              },
              {
                "InterpMode": "RCIM_Cubic",
                "TangentMode": "RCTM_Auto",
                "TangentWeightMode": "RCTWM_WeightedNone",
                "Time": 2.4333334,
                "Value": -1.103524,
                "ArriveTangent": 0.0055503896,
                "ArriveTangentWeight": 0.0,
                "LeaveTangent": 0.0055503896,
                "LeaveTangentWeight": 0.0
              },
              {
                "InterpMode": "RCIM_Cubic",
                "TangentMode": "RCTM_Auto",
                "TangentWeightMode": "RCTWM_WeightedNone",
                "Time": 2.4666667,
                "Value": -1.103356,
                "ArriveTangent": 0.0044846577,
                "ArriveTangentWeight": 0.0,
                "LeaveTangent": 0.0044846577,
                "LeaveTangentWeight": 0.0
              },
              {
                "InterpMode": "RCIM_Cubic",
                "TangentMode": "RCTM_Auto",
                "TangentWeightMode": "RCTWM_WeightedNone",
                "Time": 2.5,
                "Value": -1.103225,
                "ArriveTangent": 0.002839568,
                "ArriveTangentWeight": 0.0,
                "LeaveTangent": 0.002839568,
                "LeaveTangentWeight": 0.0
              },
              {
                "InterpMode": "RCIM_Cubic",
                "TangentMode": "RCTM_Auto",
                "TangentWeightMode": "RCTWM_WeightedNone",
                "Time": 2.5666666,
                "Value": -1.103072,
                "ArriveTangent": 0.0017297284,
                "ArriveTangentWeight": 0.0,
                "LeaveTangent": 0.0017297284,
                "LeaveTangentWeight": 0.0
              },
              {
                "InterpMode": "RCIM_Cubic",
                "TangentMode": "RCTM_Auto",
                "TangentWeightMode": "RCTWM_WeightedNone",
                "Time": 2.6,
                "Value": -1.103052,
                "ArriveTangent": 0.00030040662,
                "ArriveTangentWeight": 0.0,
                "LeaveTangent": 0.00030040662,
                "LeaveTangentWeight": 0.0
              },
              {
                "InterpMode": "RCIM_Cubic",
                "TangentMode": "RCTM_Auto",
                "TangentWeightMode": "RCTWM_WeightedNone",
                "Time": 2.6333334,
                "Value": -1.103052,
                "ArriveTangent": 0.0,
                "ArriveTangentWeight": 0.0,
                "LeaveTangent": 0.0,
                "LeaveTangentWeight": 0.0
              },
              {
                "InterpMode": "RCIM_Cubic",
                "TangentMode": "RCTM_Auto",
                "TangentWeightMode": "RCTWM_WeightedNone",
                "Time": 2.6666667,
                "Value": -1.103052,
                "ArriveTangent": 0.0,
                "ArriveTangentWeight": 0.0,
                "LeaveTangent": 0.0,
                "LeaveTangentWeight": 0.0
              }
            ],
            "DefaultValue": 3.4028235E+38,
            "PreInfinityExtrap": "RCCE_Constant",
            "PostInfinityExtrap": "RCCE_Constant"
          },
          "Name": {
            "DisplayName": "hipOffsetTY"
          },
          "CurveTypeFlags": 4
        },
        {
          "FloatCurve": {
            "Keys": [
              {
                "InterpMode": "RCIM_Cubic",
                "TangentMode": "RCTM_Auto",
                "TangentWeightMode": "RCTWM_WeightedNone",
                "Time": 0.0,
                "Value": -0.010782,
                "ArriveTangent": 0.0014618876,
                "ArriveTangentWeight": 0.0,
                "LeaveTangent": 0.0014618876,
                "LeaveTangentWeight": 0.0
              },
              {
                "InterpMode": "RCIM_Cubic",
                "TangentMode": "RCTM_Auto",
                "TangentWeightMode": "RCTWM_WeightedNone",
                "Time": 0.033333335,
                "Value": -0.01073327,
                "ArriveTangent": 0.0017029978,
                "ArriveTangentWeight": 0.0,
                "LeaveTangent": 0.0017029978,
                "LeaveTangentWeight": 0.0
              },
              {
                "InterpMode": "RCIM_Cubic",
                "TangentMode": "RCTM_Auto",
                "TangentWeightMode": "RCTWM_WeightedNone",
                "Time": 0.1,
                "Value": -0.0106117,
                "ArriveTangent": 0.0020534266,
                "ArriveTangentWeight": 0.0,
                "LeaveTangent": 0.0020534266,
                "LeaveTangentWeight": 0.0
              },
              {
                "InterpMode": "RCIM_Cubic",
                "TangentMode": "RCTM_Auto",
                "TangentWeightMode": "RCTWM_WeightedNone",
                "Time": 0.16666667,
                "Value": -0.01045948,
                "ArriveTangent": 0.002499372,
                "ArriveTangentWeight": 0.0,
                "LeaveTangent": 0.002499372,
                "LeaveTangentWeight": 0.0
              },
              {
                "InterpMode": "RCIM_Cubic",
                "TangentMode": "RCTM_Auto",
                "TangentWeightMode": "RCTWM_WeightedNone",
                "Time": 0.23333333,
                "Value": -0.01027845,
                "ArriveTangent": 0.0029177961,
                "ArriveTangentWeight": 0.0,
                "LeaveTangent": 0.0029177961,
                "LeaveTangentWeight": 0.0
              },
              {
                "InterpMode": "RCIM_Cubic",
                "TangentMode": "RCTM_Auto",
                "TangentWeightMode": "RCTWM_WeightedNone",
                "Time": 0.3,
                "Value": -0.01007044,
                "ArriveTangent": 0.0033997502,
                "ArriveTangentWeight": 0.0,
                "LeaveTangent": 0.0033997502,
                "LeaveTangentWeight": 0.0
              },
              {
                "InterpMode": "RCIM_Cubic",
                "TangentMode": "RCTM_Auto",
                "TangentWeightMode": "RCTWM_WeightedNone",
                "Time": 0.4,
                "Value": -0.009711825,
                "ArriveTangent": 0.0038382367,
                "ArriveTangentWeight": 0.0,
                "LeaveTangent": 0.0038382367,
                "LeaveTangentWeight": 0.0
              },
              {
                "InterpMode": "RCIM_Cubic",
                "TangentMode": "RCTM_Auto",
                "TangentWeightMode": "RCTWM_WeightedNone",
                "Time": 0.5,
                "Value": -0.009302793,
                "ArriveTangent": 0.004512221,
                "ArriveTangentWeight": 0.0,
                "LeaveTangent": 0.004512221,
                "LeaveTangentWeight": 0.0
              },
              {
                "InterpMode": "RCIM_Cubic",
                "TangentMode": "RCTM_Auto",
                "TangentWeightMode": "RCTWM_WeightedNone",
                "Time": 0.7,
                "Value": -0.008358159,
                "ArriveTangent": 0.0050421655,
                "ArriveTangentWeight": 0.0,
                "LeaveTangent": 0.0050421655,
                "LeaveTangentWeight": 0.0
              },
              {
                "InterpMode": "RCIM_Cubic",
                "TangentMode": "RCTM_Auto",
                "TangentWeightMode": "RCTWM_WeightedNone",
                "Time": 0.9,
                "Value": -0.007285927,
                "ArriveTangent": 0.005469207,
                "ArriveTangentWeight": 0.0,
                "LeaveTangent": 0.005469207,
                "LeaveTangentWeight": 0.0
              },
              {
                "InterpMode": "RCIM_Cubic",
                "TangentMode": "RCTM_Auto",
                "TangentWeightMode": "RCTWM_WeightedNone",
                "Time": 1.0,
                "Value": -0.006717397,
                "ArriveTangent": 0.0057521774,
                "ArriveTangentWeight": 0.0,
                "LeaveTangent": 0.0057521774,
                "LeaveTangentWeight": 0.0
              },
              {
                "InterpMode": "RCIM_Cubic",
                "TangentMode": "RCTM_Auto",
                "TangentWeightMode": "RCTWM_WeightedNone",
                "Time": 1.1,
                "Value": -0.006135491,
                "ArriveTangent": 0.005870517,
                "ArriveTangentWeight": 0.0,
                "LeaveTangent": 0.005870517,
                "LeaveTangentWeight": 0.0
              },
              {
                "InterpMode": "RCIM_Cubic",
                "TangentMode": "RCTM_Auto",
                "TangentWeightMode": "RCTWM_WeightedNone",
                "Time": 1.3,
                "Value": -0.004956242,
                "ArriveTangent": 0.0058447956,
                "ArriveTangentWeight": 0.0,
                "LeaveTangent": 0.0058447956,
                "LeaveTangentWeight": 0.0
              },
              {
                "InterpMode": "RCIM_Cubic",
                "TangentMode": "RCTM_Auto",
                "TangentWeightMode": "RCTWM_WeightedNone",
                "Time": 1.5,
                "Value": -0.003797573,
                "ArriveTangent": 0.0057161693,
                "ArriveTangentWeight": 0.0,
                "LeaveTangent": 0.0057161693,
                "LeaveTangentWeight": 0.0
              },
              {
                "InterpMode": "RCIM_Cubic",
                "TangentMode": "RCTM_Auto",
                "TangentWeightMode": "RCTWM_WeightedNone",
                "Time": 1.6,
                "Value": -0.003241391,
                "ArriveTangent": 0.005443479,
                "ArriveTangentWeight": 0.0,
                "LeaveTangent": 0.005443479,
                "LeaveTangentWeight": 0.0
              },
              {
                "InterpMode": "RCIM_Cubic",
                "TangentMode": "RCTM_Auto",
                "TangentWeightMode": "RCTWM_WeightedNone",
                "Time": 1.7,
                "Value": -0.002708877,
                "ArriveTangent": 0.0051759365,
                "ArriveTangentWeight": 0.0,
                "LeaveTangent": 0.0051759365,
                "LeaveTangentWeight": 0.0
              },
              {
                "InterpMode": "RCIM_Cubic",
                "TangentMode": "RCTM_Auto",
                "TangentWeightMode": "RCTWM_WeightedNone",
                "Time": 1.8,
                "Value": -0.002206204,
                "ArriveTangent": 0.0048466516,
                "ArriveTangentWeight": 0.0,
                "LeaveTangent": 0.0048466516,
                "LeaveTangentWeight": 0.0
              },
              {
                "InterpMode": "RCIM_Cubic",
                "TangentMode": "RCTM_Auto",
                "TangentWeightMode": "RCTWM_WeightedNone",
                "Time": 1.9,
                "Value": -0.001739547,
                "ArriveTangent": 0.0044556237,
                "ArriveTangentWeight": 0.0,
                "LeaveTangent": 0.0044556237,
                "LeaveTangentWeight": 0.0
              },
              {
                "InterpMode": "RCIM_Cubic",
                "TangentMode": "RCTM_Auto",
                "TangentWeightMode": "RCTWM_WeightedNone",
                "Time": 2.0,
                "Value": -0.001315079,
                "ArriveTangent": 0.0040028645,
                "ArriveTangentWeight": 0.0,
                "LeaveTangent": 0.0040028645,
                "LeaveTangentWeight": 0.0
              },
              {
                "InterpMode": "RCIM_Cubic",
                "TangentMode": "RCTM_Auto",
                "TangentWeightMode": "RCTWM_WeightedNone",
                "Time": 2.1,
                "Value": -0.0009389744,
                "ArriveTangent": 0.0034883555,
                "ArriveTangentWeight": 0.0,
                "LeaveTangent": 0.0034883555,
                "LeaveTangentWeight": 0.0
              },
              {
                "InterpMode": "RCIM_Cubic",
                "TangentMode": "RCTM_Auto",
                "TangentWeightMode": "RCTWM_WeightedNone",
                "Time": 2.2,
                "Value": -0.0006174078,
                "ArriveTangent": 0.0029121062,
                "ArriveTangentWeight": 0.0,
                "LeaveTangent": 0.0029121062,
                "LeaveTangentWeight": 0.0
              },
              {
                "InterpMode": "RCIM_Cubic",
                "TangentMode": "RCTM_Auto",
                "TangentWeightMode": "RCTWM_WeightedNone",
                "Time": 2.3,
                "Value": -0.000356553,
                "ArriveTangent": 0.002274118,
                "ArriveTangentWeight": 0.0,
                "LeaveTangent": 0.002274118,
                "LeaveTangentWeight": 0.0
              },
              {
                "InterpMode": "RCIM_Cubic",
                "TangentMode": "RCTM_Auto",
                "TangentWeightMode": "RCTWM_WeightedNone",
                "Time": 2.4,
                "Value": -0.0001625841,
                "ArriveTangent": 0.0015743895,
                "ArriveTangentWeight": 0.0,
                "LeaveTangent": 0.0015743895,
                "LeaveTangentWeight": 0.0
              },
              {
                "InterpMode": "RCIM_Cubic",
                "TangentMode": "RCTM_Auto",
                "TangentWeightMode": "RCTWM_WeightedNone",
                "Time": 2.5,
                "Value": -4.167503E-05,
                "ArriveTangent": 0.00094726484,
                "ArriveTangentWeight": 0.0,
                "LeaveTangent": 0.00094726484,
                "LeaveTangentWeight": 0.0
              },
              {
                "InterpMode": "RCIM_Cubic",
                "TangentMode": "RCTM_Auto",
                "TangentWeightMode": "RCTWM_WeightedNone",
                "Time": 2.5666666,
                "Value": -4.706782E-06,
                "ArriveTangent": 0.0004167507,
                "ArriveTangentWeight": 0.0,
                "LeaveTangent": 0.0004167507,
                "LeaveTangentWeight": 0.0
              },
              {
                "InterpMode": "RCIM_Cubic",
                "TangentMode": "RCTM_Auto",
                "TangentWeightMode": "RCTWM_WeightedNone",
                "Time": 2.6,
                "Value": 0.0,
                "ArriveTangent": 7.060154E-05,
                "ArriveTangentWeight": 0.0,
                "LeaveTangent": 7.060154E-05,
                "LeaveTangentWeight": 0.0
              },
              {
                "InterpMode": "RCIM_Cubic",
                "TangentMode": "RCTM_Auto",
                "TangentWeightMode": "RCTWM_WeightedNone",
                "Time": 2.6333334,
                "Value": 0.0,
                "ArriveTangent": 0.0,
                "ArriveTangentWeight": 0.0,
                "LeaveTangent": 0.0,
                "LeaveTangentWeight": 0.0
              },
              {
                "InterpMode": "RCIM_Cubic",
                "TangentMode": "RCTM_Auto",
                "TangentWeightMode": "RCTWM_WeightedNone",
                "Time": 2.6666667,
                "Value": 0.0,
                "ArriveTangent": 0.0,
                "ArriveTangentWeight": 0.0,
                "LeaveTangent": 0.0,
                "LeaveTangentWeight": 0.0
              }
            ],
            "DefaultValue": 3.4028235E+38,
            "PreInfinityExtrap": "RCCE_Constant",
            "PostInfinityExtrap": "RCCE_Constant"
          },
          "Name": {
            "DisplayName": "hipOffsetTZ"
          },
          "CurveTypeFlags": 4
        },
        {
          "FloatCurve": {
            "Keys": [
              {
                "InterpMode": "RCIM_Linear",
                "TangentMode": "RCTM_Auto",
                "TangentWeightMode": "RCTWM_WeightedNone",
                "Time": 0.0,
                "Value": 4.0,
                "ArriveTangent": 0.0,
                "ArriveTangentWeight": 0.0,
                "LeaveTangent": 0.0,
                "LeaveTangentWeight": 0.0
              }
            ],
            "DefaultValue": 3.4028235E+38,
            "PreInfinityExtrap": "RCCE_Constant",
            "PostInfinityExtrap": "RCCE_Constant"
          },
          "Name": {
            "DisplayName": "HookClav"
          },
          "CurveTypeFlags": 4
        },
        {
          "FloatCurve": {
            "Keys": [
              {
                "InterpMode": "RCIM_Linear",
                "TangentMode": "RCTM_Auto",
                "TangentWeightMode": "RCTWM_WeightedNone",
                "Time": 0.0,
                "Value": 2.0,
                "ArriveTangent": 0.0,
                "ArriveTangentWeight": 0.0,
                "LeaveTangent": 0.0,
                "LeaveTangentWeight": 0.0
              }
            ],
            "DefaultValue": 3.4028235E+38,
            "PreInfinityExtrap": "RCCE_Constant",
            "PostInfinityExtrap": "RCCE_Constant"
          },
          "Name": {
            "DisplayName": "HookSkinNeck"
          },
          "CurveTypeFlags": 4
        },
        {
          "FloatCurve": {
            "Keys": [
              {
                "InterpMode": "RCIM_Linear",
                "TangentMode": "RCTM_Auto",
                "TangentWeightMode": "RCTWM_WeightedNone",
                "Time": 0.0,
                "Value": 2.0,
                "ArriveTangent": 0.0,
                "ArriveTangentWeight": 0.0,
                "LeaveTangent": 0.0,
                "LeaveTangentWeight": 0.0
              }
            ],
            "DefaultValue": 3.4028235E+38,
            "PreInfinityExtrap": "RCCE_Constant",
            "PostInfinityExtrap": "RCCE_Constant"
          },
          "Name": {
            "DisplayName": "HookSkinNeckLT"
          },
          "CurveTypeFlags": 4
        },
        {
          "FloatCurve": {
            "Keys": [
              {
                "InterpMode": "RCIM_Linear",
                "TangentMode": "RCTM_Auto",
                "TangentWeightMode": "RCTWM_WeightedNone",
                "Time": 0.0,
                "Value": 2.0,
                "ArriveTangent": 0.0,
                "ArriveTangentWeight": 0.0,
                "LeaveTangent": 0.0,
                "LeaveTangentWeight": 0.0
              }
            ],
            "DefaultValue": 3.4028235E+38,
            "PreInfinityExtrap": "RCCE_Constant",
            "PostInfinityExtrap": "RCCE_Constant"
          },
          "Name": {
            "DisplayName": "HookSkinNeckOff"
          },
          "CurveTypeFlags": 4
        },
        {
          "FloatCurve": {
            "Keys": [
              {
                "InterpMode": "RCIM_Linear",
                "TangentMode": "RCTM_Auto",
                "TangentWeightMode": "RCTWM_WeightedNone",
                "Time": 0.0,
                "Value": 2.0,
                "ArriveTangent": 0.0,
                "ArriveTangentWeight": 0.0,
                "LeaveTangent": 0.0,
                "LeaveTangentWeight": 0.0
              }
            ],
            "DefaultValue": 3.4028235E+38,
            "PreInfinityExtrap": "RCCE_Constant",
            "PostInfinityExtrap": "RCCE_Constant"
          },
          "Name": {
            "DisplayName": "KneeRollLT"
          },
          "CurveTypeFlags": 4
        },
        {
          "FloatCurve": {
            "Keys": [
              {
                "InterpMode": "RCIM_Linear",
                "TangentMode": "RCTM_Auto",
                "TangentWeightMode": "RCTWM_WeightedNone",
                "Time": 0.0,
                "Value": 2.0,
                "ArriveTangent": 0.0,
                "ArriveTangentWeight": 0.0,
                "LeaveTangent": 0.0,
                "LeaveTangentWeight": 0.0
              }
            ],
            "DefaultValue": 3.4028235E+38,
            "PreInfinityExtrap": "RCCE_Constant",
            "PostInfinityExtrap": "RCCE_Constant"
          },
          "Name": {
            "DisplayName": "KneeRollRT"
          },
          "CurveTypeFlags": 4
        },
        {
          "FloatCurve": {
            "Keys": [
              {
                "InterpMode": "RCIM_Linear",
                "TangentMode": "RCTM_Auto",
                "TangentWeightMode": "RCTWM_WeightedNone",
                "Time": 0.0,
                "Value": 2.0,
                "ArriveTangent": 0.0,
                "ArriveTangentWeight": 0.0,
                "LeaveTangent": 0.0,
                "LeaveTangentWeight": 0.0
              }
            ],
            "DefaultValue": 3.4028235E+38,
            "PreInfinityExtrap": "RCCE_Constant",
            "PostInfinityExtrap": "RCCE_Constant"
          },
          "Name": {
            "DisplayName": "LegLT"
          },
          "CurveTypeFlags": 4
        },
        {
          "FloatCurve": {
            "Keys": [
              {
                "InterpMode": "RCIM_Linear",
                "TangentMode": "RCTM_Auto",
                "TangentWeightMode": "RCTWM_WeightedNone",
                "Time": 0.0,
                "Value": 2.0,
                "ArriveTangent": 0.0,
                "ArriveTangentWeight": 0.0,
                "LeaveTangent": 0.0,
                "LeaveTangentWeight": 0.0
              }
            ],
            "DefaultValue": 3.4028235E+38,
            "PreInfinityExtrap": "RCCE_Constant",
            "PostInfinityExtrap": "RCCE_Constant"
          },
          "Name": {
            "DisplayName": "LegRT"
          },
          "CurveTypeFlags": 4
        },
        {
          "FloatCurve": {
            "Keys": [
              {
                "InterpMode": "RCIM_Linear",
                "TangentMode": "RCTM_Auto",
                "TangentWeightMode": "RCTWM_WeightedNone",
                "Time": 0.0,
                "Value": 2.0,
                "ArriveTangent": 0.0,
                "ArriveTangentWeight": 0.0,
                "LeaveTangent": 0.0,
                "LeaveTangentWeight": 0.0
              }
            ],
            "DefaultValue": 3.4028235E+38,
            "PreInfinityExtrap": "RCCE_Constant",
            "PostInfinityExtrap": "RCCE_Constant"
          },
          "Name": {
            "DisplayName": "Neck"
          },
          "CurveTypeFlags": 4
        },
        {
          "FloatCurve": {
            "Keys": [
              {
                "InterpMode": "RCIM_Linear",
                "TangentMode": "RCTM_Auto",
                "TangentWeightMode": "RCTWM_WeightedNone",
                "Time": 0.0,
                "Value": 3.0,
                "ArriveTangent": 0.0,
                "ArriveTangentWeight": 0.0,
                "LeaveTangent": 0.0,
                "LeaveTangentWeight": 0.0
              }
            ],
            "DefaultValue": 3.4028235E+38,
            "PreInfinityExtrap": "RCCE_Constant",
            "PostInfinityExtrap": "RCCE_Constant"
          },
          "Name": {
            "DisplayName": "ShoulderRollLT"
          },
          "CurveTypeFlags": 4
        },
        {
          "FloatCurve": {
            "Keys": [
              {
                "InterpMode": "RCIM_Linear",
                "TangentMode": "RCTM_Auto",
                "TangentWeightMode": "RCTWM_WeightedNone",
                "Time": 0.0,
                "Value": 2.0,
                "ArriveTangent": 0.0,
                "ArriveTangentWeight": 0.0,
                "LeaveTangent": 0.0,
                "LeaveTangentWeight": 0.0
              }
            ],
            "DefaultValue": 3.4028235E+38,
            "PreInfinityExtrap": "RCCE_Constant",
            "PostInfinityExtrap": "RCCE_Constant"
          },
          "Name": {
            "DisplayName": "ShoulderRollOffLT"
          },
          "CurveTypeFlags": 4
        },
        {
          "FloatCurve": {
            "Keys": [
              {
                "InterpMode": "RCIM_Linear",
                "TangentMode": "RCTM_Auto",
                "TangentWeightMode": "RCTWM_WeightedNone",
                "Time": 0.0,
                "Value": 2.0,
                "ArriveTangent": 0.0,
                "ArriveTangentWeight": 0.0,
                "LeaveTangent": 0.0,
                "LeaveTangentWeight": 0.0
              }
            ],
            "DefaultValue": 3.4028235E+38,
            "PreInfinityExtrap": "RCCE_Constant",
            "PostInfinityExtrap": "RCCE_Constant"
          },
          "Name": {
            "DisplayName": "ShoulderRollOffRT"
          },
          "CurveTypeFlags": 4
        },
        {
          "FloatCurve": {
            "Keys": [
              {
                "InterpMode": "RCIM_Linear",
                "TangentMode": "RCTM_Auto",
                "TangentWeightMode": "RCTWM_WeightedNone",
                "Time": 0.0,
                "Value": 3.0,
                "ArriveTangent": 0.0,
                "ArriveTangentWeight": 0.0,
                "LeaveTangent": 0.0,
                "LeaveTangentWeight": 0.0
              }
            ],
            "DefaultValue": 3.4028235E+38,
            "PreInfinityExtrap": "RCCE_Constant",
            "PostInfinityExtrap": "RCCE_Constant"
          },
          "Name": {
            "DisplayName": "ShoulderRollRT"
          },
          "CurveTypeFlags": 4
        },
        {
          "FloatCurve": {
            "Keys": [
              {
                "InterpMode": "RCIM_Linear",
                "TangentMode": "RCTM_Auto",
                "TangentWeightMode": "RCTWM_WeightedNone",
                "Time": 0.0,
                "Value": 1.0,
                "ArriveTangent": 0.0,
                "ArriveTangentWeight": 0.0,
                "LeaveTangent": 0.0,
                "LeaveTangentWeight": 0.0
              }
            ],
            "DefaultValue": 3.4028235E+38,
            "PreInfinityExtrap": "RCCE_Constant",
            "PostInfinityExtrap": "RCCE_Constant"
          },
          "Name": {
            "DisplayName": "Tail"
          },
          "CurveTypeFlags": 4
        },
        {
          "FloatCurve": {
            "Keys": [
              {
                "InterpMode": "RCIM_Linear",
                "TangentMode": "RCTM_Auto",
                "TangentWeightMode": "RCTWM_WeightedNone",
                "Time": 0.0,
                "Value": 2.0,
                "ArriveTangent": 0.0,
                "ArriveTangentWeight": 0.0,
                "LeaveTangent": 0.0,
                "LeaveTangentWeight": 0.0
              }
            ],
            "DefaultValue": 3.4028235E+38,
            "PreInfinityExtrap": "RCCE_Constant",
            "PostInfinityExtrap": "RCCE_Constant"
          },
          "Name": {
            "DisplayName": "Torso"
          },
          "CurveTypeFlags": 4
        }
      ]
    },
    "CompressedDataStructure": {
      "CompressedNumberOfFrames": 81,
      "KeyEncodingFormat": "AKF_PerTrackCompression",
      "TranslationCompressionFormat": "ACF_Identity",
      "RotationCompressionFormat": "ACF_Identity",
      "ScaleCompressionFormat": "ACF_Identity"
    },
    "BoneCompressionCodec": {
      "ObjectName": "AnimCompress_PerTrackCompression'DefaultAnimBoneCompressionSettings:AnimCompress_PerTrackCompression_0'",
      "ObjectPath": "Engine/Content/Animation/DefaultAnimBoneCompressionSettings"
    },
    "CurveCompressionCodec": {
      "ObjectName": "AnimCurveCompressionCodec_CompressedRichCurve'DefaultAnimCurveCompressionSettings:CurveCompressionCodec'",
      "ObjectPath": "Engine/Content/Animation/DefaultAnimCurveCompressionSettings"
    },
    "CompressedRawDataSize": 163892
  }
]