[
  {
    "Type": "Texture2D",
    "Name": "CustomizationPanel_I8B",
    "Class": "UScriptClass'Texture2D'",
    "Properties": {
      "ImportedSize": {
        "X": 1024,
        "Y": 256
      },
      "LightingGuid": "F5B64972-48B8BD13-F3FBDB9D-C647E8E2",
      "LODGroup": "TEXTUREGROUP_UI",
      "SRGB": false
    },
    "SizeX": 1024,
    "SizeY": 256,
    "PackedData": 1,
    "PixelFormat": "PF_DXT5",
    "FirstMipToSerialize": 0,
    "Mips": [
      {
        "BulkData": {
          "BulkDataFlags": "BULKDATA_SingleUse | BULKDATA_ForceInlinePayload",
          "ElementCount": 262144,
          "SizeOnDisk": 262144,
          "OffsetInFile": "0x408F6"
        },
        "SizeX": 1024,
        "SizeY": 256,
        "SizeZ": 1
      }
    ]
  }
]